<?xml version="1.0" encoding="utf-8"?>
<VisioDocument>
	<DocumentProperties>
		<Title></Title>
		<HyperlinkBase href=""></HyperlinkBase>
	</DocumentProperties>
	<Pages>
		<Page ID="0" Name="Main" NameU="Main">
			<PageProps>
				<PageScale Unit="MM">0.039370078740157</PageScale>
				<DrawingScale Unit="MM">0.039370078740157</DrawingScale>
			</PageProps>
			<Layer IX="0">
				<Name>Diagramme de flux</Name>
				<NameUniv>Flowchart</NameUniv>
				<Visible>1</Visible>
			</Layer>
			<Layer IX="1">
				<Name>Lien</Name>
				<NameUniv>Connector</NameUniv>
				<Visible>1</Visible>
			</Layer>
			<Shapes>
				<Shape ID="1" UniqueID="{40EC6CFF-8576-4420-AFEC-94E5E6814B3C}" Name="Début/fin" NameU="Start/End" Master="2">
					<Text>Début</Text>
					<XForm>
						<PinX Unit="MM">5.511811023622046</PinX>
						<PinY Unit="MM">7.677165354330708</PinY>
					</XForm>
					<LayerMem>
						<LayerMember>0</LayerMember>
					</LayerMem>
					<Prop ID="1" Name="Cost" NameU="Cost">
						<Value></Value>
						<Label>Coût</Label>
					</Prop>
					<Prop ID="2" Name="ProcessNumber" NameU="ProcessNumber">
						<Value></Value>
						<Label>Numéro de processus</Label>
					</Prop>
					<Prop ID="3" Name="Owner" NameU="Owner">
						<Value></Value>
						<Label>Propriétaire</Label>
					</Prop>
					<Prop ID="4" Name="Function" NameU="Function">
						<Value></Value>
						<Label>Fonction</Label>
					</Prop>
					<Prop ID="5" Name="StartDate" NameU="StartDate">
						<Value></Value>
						<Label>Date de début</Label>
					</Prop>
					<Prop ID="6" Name="EndDate" NameU="EndDate">
						<Value></Value>
						<Label>Date de fin</Label>
					</Prop>
					<Prop ID="7" Name="Status" NameU="Status">
						<Value></Value>
						<Label>État</Label>
					</Prop>
				</Shape>
				<Shape ID="3" UniqueID="{4A030E7E-818A-4BF3-B6A9-5B9D8D7A4F91}" Name="Processus" NameU="Process" Master="6">
					<Text>Lancement du jeu</Text>
					<XForm>
						<PinX Unit="MM">5.511811023622046</PinX>
						<PinY Unit="MM">6.988188976377955</PinY>
					</XForm>
					<LayerMem>
						<LayerMember>0</LayerMember>
					</LayerMem>
					<Prop ID="1" Name="Cost" NameU="Cost">
						<Value></Value>
						<Label>Coût</Label>
					</Prop>
					<Prop ID="2" Name="ProcessNumber" NameU="ProcessNumber">
						<Value></Value>
						<Label>Numéro de processus</Label>
					</Prop>
					<Prop ID="3" Name="Owner" NameU="Owner">
						<Value></Value>
						<Label>Propriétaire</Label>
					</Prop>
					<Prop ID="4" Name="Function" NameU="Function">
						<Value></Value>
						<Label>Fonction</Label>
					</Prop>
					<Prop ID="5" Name="StartDate" NameU="StartDate">
						<Value></Value>
						<Label>Date de début</Label>
					</Prop>
					<Prop ID="6" Name="EndDate" NameU="EndDate">
						<Value></Value>
						<Label>Date de fin</Label>
					</Prop>
					<Prop ID="7" Name="Status" NameU="Status">
						<Value></Value>
						<Label>État</Label>
					</Prop>
				</Shape>
				<Shape ID="5" UniqueID="{7B6CE241-E6E5-453A-9737-5B838496B39A}" Name="Lien dynamique" NameU="Dynamic connector" Master="7">
					<XForm>
						<PinX Unit="MM">5.511811023622046</PinX>
						<PinY Unit="MM">7.381889763779528</PinY>
					</XForm>
					<LayerMem>
						<LayerMember>1</LayerMember>
					</LayerMem>
				</Shape>
				<Shape ID="9" UniqueID="{9E19E6B4-AE6D-4FC3-B22A-BBFF277F7F0B}" Name="Lien dynamique.9" NameU="Dynamic connector.9" Master="7">
					<XForm>
						<PinX Unit="MM">5.511811023622046</PinX>
						<PinY Unit="MM">6.594488188976381</PinY>
					</XForm>
					<LayerMem>
						<LayerMember>1</LayerMember>
					</LayerMem>
				</Shape>
				<Shape ID="8" UniqueID="{F1CD6068-E3FE-417A-9E54-2903195401EC}" Name="Décision" NameU="Decision" Master="5">
					<Text>Jeu aléatoire ?</Text>
					<XForm>
						<PinX Unit="MM">5.511811023622046</PinX>
						<PinY Unit="MM">6.200787401574808</PinY>
					</XForm>
					<LayerMem>
						<LayerMember>0</LayerMember>
					</LayerMem>
					<Prop ID="1" Name="Cost" NameU="Cost">
						<Value></Value>
						<Label>Coût</Label>
					</Prop>
					<Prop ID="2" Name="ProcessNumber" NameU="ProcessNumber">
						<Value></Value>
						<Label>Numéro de processus</Label>
					</Prop>
					<Prop ID="3" Name="Owner" NameU="Owner">
						<Value></Value>
						<Label>Propriétaire</Label>
					</Prop>
					<Prop ID="4" Name="Function" NameU="Function">
						<Value></Value>
						<Label>Fonction</Label>
					</Prop>
					<Prop ID="5" Name="StartDate" NameU="StartDate">
						<Value></Value>
						<Label>Date de début</Label>
					</Prop>
					<Prop ID="6" Name="EndDate" NameU="EndDate">
						<Value></Value>
						<Label>Date de fin</Label>
					</Prop>
					<Prop ID="7" Name="Status" NameU="Status">
						<Value></Value>
						<Label>État</Label>
					</Prop>
				</Shape>
				<Shape ID="11" UniqueID="{6C829A38-8F70-4EDE-980D-61878F34D65F}" Name="Lien dynamique.11" NameU="Dynamic connector.11" Master="7">
					<Text>Oui</Text>
					<XForm>
						<PinX Unit="MM">6.299212598425196</PinX>
						<PinY Unit="MM">6.200787401574808</PinY>
					</XForm>
					<LayerMem>
						<LayerMember>1</LayerMember>
					</LayerMem>
				</Shape>
				<Shape ID="10" UniqueID="{B3DDE890-0BDF-41DB-8222-AF751636ECA2}" Name="Sous-processus" NameU="Subprocess" Master="13">
					<Text>Jeu aléatoire</Text>
					<XForm>
						<PinX Unit="MM">7.086614173228345</PinX>
						<PinY Unit="MM">6.200787401574807</PinY>
					</XForm>
					<LayerMem>
						<LayerMember>0</LayerMember>
					</LayerMem>
					<Prop ID="1" Name="Cost" NameU="Cost">
						<Value></Value>
						<Label>Coût</Label>
					</Prop>
					<Prop ID="2" Name="ProcessNumber" NameU="ProcessNumber">
						<Value></Value>
						<Label>Numéro de processus</Label>
					</Prop>
					<Prop ID="3" Name="Owner" NameU="Owner">
						<Value></Value>
						<Label>Propriétaire</Label>
					</Prop>
					<Prop ID="4" Name="Function" NameU="Function">
						<Value></Value>
						<Label>Fonction</Label>
					</Prop>
					<Prop ID="5" Name="StartDate" NameU="StartDate">
						<Value></Value>
						<Label>Date de début</Label>
					</Prop>
					<Prop ID="6" Name="EndDate" NameU="EndDate">
						<Value></Value>
						<Label>Date de fin</Label>
					</Prop>
					<Prop ID="7" Name="Status" NameU="Status">
						<Value></Value>
						<Label>État</Label>
					</Prop>
				</Shape>
				<Shape ID="13" UniqueID="{BBD6D1A6-E839-4A18-BBB8-9A67A22D2AB0}" Name="Lien dynamique.13" NameU="Dynamic connector.13" Master="7">
					<Text>Non</Text>
					<XForm>
						<PinX Unit="MM">4.724409448818896</PinX>
						<PinY Unit="MM">6.200787401574808</PinY>
					</XForm>
					<LayerMem>
						<LayerMember>1</LayerMember>
					</LayerMem>
				</Shape>
				<Shape ID="12" UniqueID="{6E34F24D-2D54-4D8E-87F7-D99B8FFDCF85}" Name="Sous-processus.12" NameU="Subprocess.12" Master="13">
					<Text>Jeu manuel</Text>
					<XForm>
						<PinX Unit="MM">3.937007874015747</PinX>
						<PinY Unit="MM">6.200787401574807</PinY>
					</XForm>
					<LayerMem>
						<LayerMember>0</LayerMember>
					</LayerMem>
					<Prop ID="1" Name="Cost" NameU="Cost">
						<Value></Value>
						<Label>Coût</Label>
					</Prop>
					<Prop ID="2" Name="ProcessNumber" NameU="ProcessNumber">
						<Value></Value>
						<Label>Numéro de processus</Label>
					</Prop>
					<Prop ID="3" Name="Owner" NameU="Owner">
						<Value></Value>
						<Label>Propriétaire</Label>
					</Prop>
					<Prop ID="4" Name="Function" NameU="Function">
						<Value></Value>
						<Label>Fonction</Label>
					</Prop>
					<Prop ID="5" Name="StartDate" NameU="StartDate">
						<Value></Value>
						<Label>Date de début</Label>
					</Prop>
					<Prop ID="6" Name="EndDate" NameU="EndDate">
						<Value></Value>
						<Label>Date de fin</Label>
					</Prop>
					<Prop ID="7" Name="Status" NameU="Status">
						<Value></Value>
						<Label>État</Label>
					</Prop>
				</Shape>
				<Shape ID="18" UniqueID="{AC7D3BEA-E3D9-4070-B829-505BA8CF1618}" Name="Décision.18" NameU="Decision.18" Master="5">
					<Text>Jeu en cours ?</Text>
					<XForm>
						<PinX Unit="MM">5.511811023622048</PinX>
						<PinY Unit="MM">4.507874015748030</PinY>
					</XForm>
					<LayerMem>
						<LayerMember>0</LayerMember>
					</LayerMem>
					<Prop ID="1" Name="Cost" NameU="Cost">
						<Value></Value>
						<Label>Coût</Label>
					</Prop>
					<Prop ID="2" Name="ProcessNumber" NameU="ProcessNumber">
						<Value></Value>
						<Label>Numéro de processus</Label>
					</Prop>
					<Prop ID="3" Name="Owner" NameU="Owner">
						<Value></Value>
						<Label>Propriétaire</Label>
					</Prop>
					<Prop ID="4" Name="Function" NameU="Function">
						<Value></Value>
						<Label>Fonction</Label>
					</Prop>
					<Prop ID="5" Name="StartDate" NameU="StartDate">
						<Value></Value>
						<Label>Date de début</Label>
					</Prop>
					<Prop ID="6" Name="EndDate" NameU="EndDate">
						<Value></Value>
						<Label>Date de fin</Label>
					</Prop>
					<Prop ID="7" Name="Status" NameU="Status">
						<Value></Value>
						<Label>État</Label>
					</Prop>
				</Shape>
				<Shape ID="22" UniqueID="{E96F94B8-5D53-4422-87B9-E053F51628B0}" Name="Lien dynamique.22" NameU="Dynamic connector.22" Master="7">
					<XForm>
						<PinX Unit="MM">6.299212598425198</PinX>
						<PinY Unit="MM">4.507874015748031</PinY>
					</XForm>
					<LayerMem>
						<LayerMember>1</LayerMember>
					</LayerMem>
				</Shape>
				<Shape ID="21" UniqueID="{8A80AEF1-059E-4607-BD74-DB8A035DEFF9}" Name="Processus.21" NameU="Process.21" Master="6">
					<Text>Le jeu demande une confirmation </Text>
					<XForm>
						<PinX Unit="MM">7.086614173228348</PinX>
						<PinY Unit="MM">4.507874015748029</PinY>
					</XForm>
					<LayerMem>
						<LayerMember>0</LayerMember>
					</LayerMem>
					<Prop ID="1" Name="Cost" NameU="Cost">
						<Value></Value>
						<Label>Coût</Label>
					</Prop>
					<Prop ID="2" Name="ProcessNumber" NameU="ProcessNumber">
						<Value></Value>
						<Label>Numéro de processus</Label>
					</Prop>
					<Prop ID="3" Name="Owner" NameU="Owner">
						<Value></Value>
						<Label>Propriétaire</Label>
					</Prop>
					<Prop ID="4" Name="Function" NameU="Function">
						<Value></Value>
						<Label>Fonction</Label>
					</Prop>
					<Prop ID="5" Name="StartDate" NameU="StartDate">
						<Value></Value>
						<Label>Date de début</Label>
					</Prop>
					<Prop ID="6" Name="EndDate" NameU="EndDate">
						<Value></Value>
						<Label>Date de fin</Label>
					</Prop>
					<Prop ID="7" Name="Status" NameU="Status">
						<Value></Value>
						<Label>État</Label>
					</Prop>
				</Shape>
				<Shape ID="24" UniqueID="{08A9F4CF-ED27-4291-B507-0AFCA2908A00}" Name="Lien dynamique.24" NameU="Dynamic connector.24" Master="7">
					<Text>Non</Text>
					<XForm>
						<PinX Unit="MM">4.724409448818899</PinX>
						<PinY Unit="MM">4.507874015748031</PinY>
					</XForm>
					<LayerMem>
						<LayerMember>1</LayerMember>
					</LayerMem>
				</Shape>
				<Shape ID="23" UniqueID="{26C985C5-6F69-49EE-B494-46007F2D9290}" Name="Processus.23" NameU="Process.23" Master="6">
					<Text>Le jeu s’arrête</Text>
					<XForm>
						<PinX Unit="MM">3.937007874015750</PinX>
						<PinY Unit="MM">4.507874015748029</PinY>
					</XForm>
					<LayerMem>
						<LayerMember>0</LayerMember>
					</LayerMem>
					<Prop ID="1" Name="Cost" NameU="Cost">
						<Value></Value>
						<Label>Coût</Label>
					</Prop>
					<Prop ID="2" Name="ProcessNumber" NameU="ProcessNumber">
						<Value></Value>
						<Label>Numéro de processus</Label>
					</Prop>
					<Prop ID="3" Name="Owner" NameU="Owner">
						<Value></Value>
						<Label>Propriétaire</Label>
					</Prop>
					<Prop ID="4" Name="Function" NameU="Function">
						<Value></Value>
						<Label>Fonction</Label>
					</Prop>
					<Prop ID="5" Name="StartDate" NameU="StartDate">
						<Value></Value>
						<Label>Date de début</Label>
					</Prop>
					<Prop ID="6" Name="EndDate" NameU="EndDate">
						<Value></Value>
						<Label>Date de fin</Label>
					</Prop>
					<Prop ID="7" Name="Status" NameU="Status">
						<Value></Value>
						<Label>État</Label>
					</Prop>
				</Shape>
				<Shape ID="26" UniqueID="{3A203D1D-41E9-4383-B329-94A0F04FEFE5}" Name="Lien dynamique.26" NameU="Dynamic connector.26" Master="7">
					<XForm>
						<PinX Unit="MM">7.086614173228348</PinX>
						<PinY Unit="MM">3.917322834645665</PinY>
					</XForm>
					<LayerMem>
						<LayerMember>1</LayerMember>
					</LayerMem>
				</Shape>
				<Shape ID="25" UniqueID="{057136D9-FCAD-4254-9F60-59B4F01A4262}" Name="Décision.25" NameU="Decision.25" Master="5">
					<Text>La demande confirmée ?</Text>
					<XForm>
						<PinX Unit="MM">7.086614173228348</PinX>
						<PinY Unit="MM">3.326771653543304</PinY>
					</XForm>
					<LayerMem>
						<LayerMember>0</LayerMember>
					</LayerMem>
					<Prop ID="1" Name="Cost" NameU="Cost">
						<Value></Value>
						<Label>Coût</Label>
					</Prop>
					<Prop ID="2" Name="ProcessNumber" NameU="ProcessNumber">
						<Value></Value>
						<Label>Numéro de processus</Label>
					</Prop>
					<Prop ID="3" Name="Owner" NameU="Owner">
						<Value></Value>
						<Label>Propriétaire</Label>
					</Prop>
					<Prop ID="4" Name="Function" NameU="Function">
						<Value></Value>
						<Label>Fonction</Label>
					</Prop>
					<Prop ID="5" Name="StartDate" NameU="StartDate">
						<Value></Value>
						<Label>Date de début</Label>
					</Prop>
					<Prop ID="6" Name="EndDate" NameU="EndDate">
						<Value></Value>
						<Label>Date de fin</Label>
					</Prop>
					<Prop ID="7" Name="Status" NameU="Status">
						<Value></Value>
						<Label>État</Label>
					</Prop>
				</Shape>
				<Shape ID="28" UniqueID="{664B4C8B-7EBF-473D-86D0-49E8FC906F7C}" Name="Lien dynamique.28" NameU="Dynamic connector.28" Master="7">
					<Text>Oui</Text>
					<XForm>
						<PinX Unit="MM">7.874015748031497</PinX>
						<PinY Unit="MM">3.326771653543304</PinY>
					</XForm>
					<LayerMem>
						<LayerMember>1</LayerMember>
					</LayerMem>
				</Shape>
				<Shape ID="27" UniqueID="{3C6CA5C9-819F-48A8-9747-4C3AA7E49ED1}" Name="Processus.27" NameU="Process.27" Master="6">
					<Text>Le jeu s’arrête</Text>
					<XForm>
						<PinX Unit="MM">8.661417322834646</PinX>
						<PinY Unit="MM">3.326771653543304</PinY>
					</XForm>
					<LayerMem>
						<LayerMember>0</LayerMember>
					</LayerMem>
					<Prop ID="1" Name="Cost" NameU="Cost">
						<Value></Value>
						<Label>Coût</Label>
					</Prop>
					<Prop ID="2" Name="ProcessNumber" NameU="ProcessNumber">
						<Value></Value>
						<Label>Numéro de processus</Label>
					</Prop>
					<Prop ID="3" Name="Owner" NameU="Owner">
						<Value></Value>
						<Label>Propriétaire</Label>
					</Prop>
					<Prop ID="4" Name="Function" NameU="Function">
						<Value></Value>
						<Label>Fonction</Label>
					</Prop>
					<Prop ID="5" Name="StartDate" NameU="StartDate">
						<Value></Value>
						<Label>Date de début</Label>
					</Prop>
					<Prop ID="6" Name="EndDate" NameU="EndDate">
						<Value></Value>
						<Label>Date de fin</Label>
					</Prop>
					<Prop ID="7" Name="Status" NameU="Status">
						<Value></Value>
						<Label>État</Label>
					</Prop>
				</Shape>
				<Shape ID="30" UniqueID="{DBBA469D-510C-45D3-BBA9-5FCA27C4FD1C}" Name="Lien dynamique.30" NameU="Dynamic connector.30" Master="7">
					<Text>Non</Text>
					<XForm>
						<PinX Unit="MM">6.299212598425198</PinX>
						<PinY Unit="MM">3.326771653543304</PinY>
					</XForm>
					<LayerMem>
						<LayerMember>1</LayerMember>
					</LayerMem>
				</Shape>
				<Shape ID="29" UniqueID="{5E560A2A-344A-4DB7-B9E3-B1F1856CFC9B}" Name="Processus.29" NameU="Process.29" Master="6">
					<Text>Le jeu reprends</Text>
					<XForm>
						<PinX Unit="MM">5.511811023622048</PinX>
						<PinY Unit="MM">3.326771653543304</PinY>
					</XForm>
					<LayerMem>
						<LayerMember>0</LayerMember>
					</LayerMem>
					<Prop ID="1" Name="Cost" NameU="Cost">
						<Value></Value>
						<Label>Coût</Label>
					</Prop>
					<Prop ID="2" Name="ProcessNumber" NameU="ProcessNumber">
						<Value></Value>
						<Label>Numéro de processus</Label>
					</Prop>
					<Prop ID="3" Name="Owner" NameU="Owner">
						<Value></Value>
						<Label>Propriétaire</Label>
					</Prop>
					<Prop ID="4" Name="Function" NameU="Function">
						<Value></Value>
						<Label>Fonction</Label>
					</Prop>
					<Prop ID="5" Name="StartDate" NameU="StartDate">
						<Value></Value>
						<Label>Date de début</Label>
					</Prop>
					<Prop ID="6" Name="EndDate" NameU="EndDate">
						<Value></Value>
						<Label>Date de fin</Label>
					</Prop>
					<Prop ID="7" Name="Status" NameU="Status">
						<Value></Value>
						<Label>État</Label>
					</Prop>
				</Shape>
				<Shape ID="34" UniqueID="{3E405C9D-D3B0-453D-8D83-AC6ADB494F95}" Name="Lien dynamique.34" NameU="Dynamic connector.34" Master="7">
					<XForm>
						<PinX Unit="MM">6.299212598425196</PinX>
						<PinY Unit="MM">5.708661417322837</PinY>
					</XForm>
					<LayerMem>
						<LayerMember>1</LayerMember>
					</LayerMem>
				</Shape>
				<Shape ID="33" UniqueID="{2C3C8A84-D895-46A5-9907-7CEC22F7D086}" Name="Processus.33" NameU="Process.33" Master="6">
					<Text>Demande d’arrêt</Text>
					<XForm>
						<PinX Unit="MM">5.511811023622046</PinX>
						<PinY Unit="MM">5.216535433070868</PinY>
					</XForm>
					<LayerMem>
						<LayerMember>0</LayerMember>
					</LayerMem>
					<Prop ID="1" Name="Cost" NameU="Cost">
						<Value></Value>
						<Label>Coût</Label>
					</Prop>
					<Prop ID="2" Name="ProcessNumber" NameU="ProcessNumber">
						<Value></Value>
						<Label>Numéro de processus</Label>
					</Prop>
					<Prop ID="3" Name="Owner" NameU="Owner">
						<Value></Value>
						<Label>Propriétaire</Label>
					</Prop>
					<Prop ID="4" Name="Function" NameU="Function">
						<Value></Value>
						<Label>Fonction</Label>
					</Prop>
					<Prop ID="5" Name="StartDate" NameU="StartDate">
						<Value></Value>
						<Label>Date de début</Label>
					</Prop>
					<Prop ID="6" Name="EndDate" NameU="EndDate">
						<Value></Value>
						<Label>Date de fin</Label>
					</Prop>
					<Prop ID="7" Name="Status" NameU="Status">
						<Value></Value>
						<Label>État</Label>
					</Prop>
				</Shape>
				<Shape ID="35" UniqueID="{3357D8D4-943B-4CEA-A2A7-229FFFA6C8C0}" Name="Lien dynamique.35" NameU="Dynamic connector.35" Master="7">
					<XForm>
						<PinX Unit="MM">4.724409448818896</PinX>
						<PinY Unit="MM">5.708661417322837</PinY>
					</XForm>
					<LayerMem>
						<LayerMember>1</LayerMember>
					</LayerMem>
				</Shape>
				<Shape ID="36" UniqueID="{ECA0910F-515B-40A4-8EEF-823480AD7A06}" Name="Lien dynamique.36" NameU="Dynamic connector.36" Master="7">
					<XForm>
						<PinX Unit="MM">5.511811023622047</PinX>
						<PinY Unit="MM">4.862204724409448</PinY>
					</XForm>
					<LayerMem>
						<LayerMember>1</LayerMember>
					</LayerMem>
				</Shape>
				<Shape ID="37" UniqueID="{4915C261-70A5-4A7F-A1F0-833789AC8BDC}" Name="Début/fin.37" NameU="Start/End.37" Master="2">
					<Text>Fin</Text>
					<XForm>
						<PinX Unit="MM">5.511811023622048</PinX>
						<PinY Unit="MM">0.590551181102362</PinY>
					</XForm>
					<LayerMem>
						<LayerMember>0</LayerMember>
					</LayerMem>
					<Prop ID="1" Name="Cost" NameU="Cost">
						<Value></Value>
						<Label>Coût</Label>
					</Prop>
					<Prop ID="2" Name="ProcessNumber" NameU="ProcessNumber">
						<Value></Value>
						<Label>Numéro de processus</Label>
					</Prop>
					<Prop ID="3" Name="Owner" NameU="Owner">
						<Value></Value>
						<Label>Propriétaire</Label>
					</Prop>
					<Prop ID="4" Name="Function" NameU="Function">
						<Value></Value>
						<Label>Fonction</Label>
					</Prop>
					<Prop ID="5" Name="StartDate" NameU="StartDate">
						<Value></Value>
						<Label>Date de début</Label>
					</Prop>
					<Prop ID="6" Name="EndDate" NameU="EndDate">
						<Value></Value>
						<Label>Date de fin</Label>
					</Prop>
					<Prop ID="7" Name="Status" NameU="Status">
						<Value></Value>
						<Label>État</Label>
					</Prop>
				</Shape>
				<Shape ID="38" UniqueID="{038DE386-CC84-4C00-B1FA-5E41159C7E61}" Name="Lien dynamique.38" NameU="Dynamic connector.38" Master="7">
					<XForm>
						<PinX Unit="MM">7.332677165354331</PinX>
						<PinY Unit="MM">1.811023622047240</PinY>
					</XForm>
					<LayerMem>
						<LayerMember>1</LayerMember>
					</LayerMem>
				</Shape>
				<Shape ID="40" UniqueID="{7B3DA1FD-F69B-4772-8EAC-AB5498807937}" Name="Lien dynamique.40" NameU="Dynamic connector.40" Master="7">
					<XForm>
						<PinX Unit="MM">8.120078740157480</PinX>
						<PinY Unit="MM">5.856299212598428</PinY>
					</XForm>
					<LayerMem>
						<LayerMember>1</LayerMember>
					</LayerMem>
				</Shape>
				<Shape ID="39" UniqueID="{E209BFD8-8E8C-4A57-8DB3-B5ECDB0DACD7}" Name="Processus.39" NameU="Process.39" Master="6">
					<Text>Le jeu est terminé</Text>
					<XForm>
						<PinX Unit="MM">8.661417322834644</PinX>
						<PinY Unit="MM">5.216535433070868</PinY>
					</XForm>
					<LayerMem>
						<LayerMember>0</LayerMember>
					</LayerMem>
					<Prop ID="1" Name="Cost" NameU="Cost">
						<Value></Value>
						<Label>Coût</Label>
					</Prop>
					<Prop ID="2" Name="ProcessNumber" NameU="ProcessNumber">
						<Value></Value>
						<Label>Numéro de processus</Label>
					</Prop>
					<Prop ID="3" Name="Owner" NameU="Owner">
						<Value></Value>
						<Label>Propriétaire</Label>
					</Prop>
					<Prop ID="4" Name="Function" NameU="Function">
						<Value></Value>
						<Label>Fonction</Label>
					</Prop>
					<Prop ID="5" Name="StartDate" NameU="StartDate">
						<Value></Value>
						<Label>Date de début</Label>
					</Prop>
					<Prop ID="6" Name="EndDate" NameU="EndDate">
						<Value></Value>
						<Label>Date de fin</Label>
					</Prop>
					<Prop ID="7" Name="Status" NameU="Status">
						<Value></Value>
						<Label>État</Label>
					</Prop>
				</Shape>
				<Shape ID="41" UniqueID="{45BB0445-250F-416C-92A3-A3D1BF5328AA}" Name="Lien dynamique.41" NameU="Dynamic connector.41" Master="7">
					<XForm>
						<PinX Unit="MM">6.299212598425196</PinX>
						<PinY Unit="MM">5.708661417322837</PinY>
					</XForm>
					<LayerMem>
						<LayerMember>1</LayerMember>
					</LayerMem>
				</Shape>
				<Shape ID="42" UniqueID="{9E5F8616-5ED4-45AD-9E01-8ECA3A7C9B13}" Name="Décision.42" NameU="Decision.42" Master="5">
					<Text>Continuer avec une nouvelle partie ?</Text>
					<XForm>
						<PinX Unit="MM">9.980314960629922</PinX>
						<PinY Unit="MM">5.216535433070867</PinY>
					</XForm>
					<LayerMem>
						<LayerMember>0</LayerMember>
					</LayerMem>
					<Prop ID="1" Name="Cost" NameU="Cost">
						<Value></Value>
						<Label>Coût</Label>
					</Prop>
					<Prop ID="2" Name="ProcessNumber" NameU="ProcessNumber">
						<Value></Value>
						<Label>Numéro de processus</Label>
					</Prop>
					<Prop ID="3" Name="Owner" NameU="Owner">
						<Value></Value>
						<Label>Propriétaire</Label>
					</Prop>
					<Prop ID="4" Name="Function" NameU="Function">
						<Value></Value>
						<Label>Fonction</Label>
					</Prop>
					<Prop ID="5" Name="StartDate" NameU="StartDate">
						<Value></Value>
						<Label>Date de début</Label>
					</Prop>
					<Prop ID="6" Name="EndDate" NameU="EndDate">
						<Value></Value>
						<Label>Date de fin</Label>
					</Prop>
					<Prop ID="7" Name="Status" NameU="Status">
						<Value></Value>
						<Label>État</Label>
					</Prop>
				</Shape>
				<Shape ID="43" UniqueID="{D8F03771-9886-4069-B95A-91D8267E388F}" Name="Lien dynamique.43" NameU="Dynamic connector.43" Master="7">
					<XForm>
						<PinX Unit="MM">9.153543307086613</PinX>
						<PinY Unit="MM">5.216535433070868</PinY>
					</XForm>
					<LayerMem>
						<LayerMember>1</LayerMember>
					</LayerMem>
				</Shape>
				<Shape ID="44" UniqueID="{15E7E6D1-6D27-4006-A786-D70CE06A239C}" Name="Lien dynamique.44" NameU="Dynamic connector.44" Master="7">
					<XForm>
						<PinX Unit="MM">9.320866141732283</PinX>
						<PinY Unit="MM">5.216535433070867</PinY>
					</XForm>
					<LayerMem>
						<LayerMember>1</LayerMember>
					</LayerMem>
				</Shape>
				<Shape ID="46" UniqueID="{1AD1A26A-8D4B-47F5-8A20-B9CCCD050962}" Name="Lien dynamique.46" NameU="Dynamic connector.46" Master="7">
					<Text>Oui</Text>
					<XForm>
						<PinX Unit="MM">7.746062992125984</PinX>
						<PinY Unit="MM">6.013779527559057</PinY>
					</XForm>
					<LayerMem>
						<LayerMember>1</LayerMember>
					</LayerMem>
				</Shape>
				<Shape ID="47" UniqueID="{113A8F1A-A8D9-414B-954B-72B455BCBCDE}" Name="Lien dynamique.47" NameU="Dynamic connector.47" Master="7">
					<Text>Non</Text>
					<XForm>
						<PinX Unit="MM">9.566929133858268</PinX>
						<PinY Unit="MM">4.114173228346456</PinY>
					</XForm>
					<LayerMem>
						<LayerMember>1</LayerMember>
					</LayerMem>
				</Shape>
			</Shapes>
		</Page>
		<Page ID="4" Name="PuzzleManuel" NameU="PuzzleManuel">
			<PageProps>
				<PageScale Unit="MM">0.039370078740157</PageScale>
				<DrawingScale Unit="MM">0.039370078740157</DrawingScale>
			</PageProps>
			<Layer IX="0">
				<Name>Diagramme de flux</Name>
				<NameUniv>Flowchart</NameUniv>
				<Visible>1</Visible>
			</Layer>
			<Layer IX="1">
				<Name>Lien</Name>
				<NameUniv>Connector</NameUniv>
				<Visible>1</Visible>
			</Layer>
			<Shapes>
				<Shape ID="1" UniqueID="{17769BDD-F8BA-4C53-9336-A21403C6B5EE}" Name="Début/fin" NameU="Start/End" Master="2">
					<Text>Debut</Text>
					<XForm>
						<PinX Unit="MM">5.846456692913385</PinX>
						<PinY Unit="MM">7.677165354330708</PinY>
					</XForm>
					<LayerMem>
						<LayerMember>0</LayerMember>
					</LayerMem>
					<Prop ID="1" Name="Cost" NameU="Cost">
						<Value></Value>
						<Label>Coût</Label>
					</Prop>
					<Prop ID="2" Name="ProcessNumber" NameU="ProcessNumber">
						<Value></Value>
						<Label>Numéro de processus</Label>
					</Prop>
					<Prop ID="3" Name="Owner" NameU="Owner">
						<Value></Value>
						<Label>Propriétaire</Label>
					</Prop>
					<Prop ID="4" Name="Function" NameU="Function">
						<Value></Value>
						<Label>Fonction</Label>
					</Prop>
					<Prop ID="5" Name="StartDate" NameU="StartDate">
						<Value></Value>
						<Label>Date de début</Label>
					</Prop>
					<Prop ID="6" Name="EndDate" NameU="EndDate">
						<Value></Value>
						<Label>Date de fin</Label>
					</Prop>
					<Prop ID="7" Name="Status" NameU="Status">
						<Value></Value>
						<Label>État</Label>
					</Prop>
				</Shape>
				<Shape ID="2" UniqueID="{0F1F61AB-0130-46F8-AB1F-51CF05E6436C}" Name="Décision" NameU="Decision" Master="5">
					<Text>Niveau de difficulté </Text>
					<XForm>
						<PinX Unit="MM">5.846456692913385</PinX>
						<PinY Unit="MM">6.594488188976379</PinY>
					</XForm>
					<LayerMem>
						<LayerMember>0</LayerMember>
					</LayerMem>
					<Prop ID="1" Name="Cost" NameU="Cost">
						<Value></Value>
						<Label>Coût</Label>
					</Prop>
					<Prop ID="2" Name="ProcessNumber" NameU="ProcessNumber">
						<Value></Value>
						<Label>Numéro de processus</Label>
					</Prop>
					<Prop ID="3" Name="Owner" NameU="Owner">
						<Value></Value>
						<Label>Propriétaire</Label>
					</Prop>
					<Prop ID="4" Name="Function" NameU="Function">
						<Value></Value>
						<Label>Fonction</Label>
					</Prop>
					<Prop ID="5" Name="StartDate" NameU="StartDate">
						<Value></Value>
						<Label>Date de début</Label>
					</Prop>
					<Prop ID="6" Name="EndDate" NameU="EndDate">
						<Value></Value>
						<Label>Date de fin</Label>
					</Prop>
					<Prop ID="7" Name="Status" NameU="Status">
						<Value></Value>
						<Label>État</Label>
					</Prop>
				</Shape>
				<Shape ID="3" UniqueID="{39EB839F-E84A-4ABB-9B33-677A7277CCFD}" Name="Lien dynamique.6" NameU="Dynamic connector.6" Master="7">
					<Text>Facile</Text>
					<XForm>
						<PinX Unit="MM">5.059055118110235</PinX>
						<PinY Unit="MM">6.594488188976379</PinY>
					</XForm>
					<LayerMem>
						<LayerMember>1</LayerMember>
					</LayerMem>
				</Shape>
				<Shape ID="4" UniqueID="{BA89C004-9AE4-4502-A257-82FB3838303B}" Name="Processus" NameU="Process" Master="6">
					<Text>Choix de la carte «facile»</Text>
					<XForm>
						<PinX Unit="MM">4.271653543307086</PinX>
						<PinY Unit="MM">6.594488188976378</PinY>
					</XForm>
					<LayerMem>
						<LayerMember>0</LayerMember>
					</LayerMem>
					<Prop ID="1" Name="Cost" NameU="Cost">
						<Value></Value>
						<Label>Coût</Label>
					</Prop>
					<Prop ID="2" Name="ProcessNumber" NameU="ProcessNumber">
						<Value></Value>
						<Label>Numéro de processus</Label>
					</Prop>
					<Prop ID="3" Name="Owner" NameU="Owner">
						<Value></Value>
						<Label>Propriétaire</Label>
					</Prop>
					<Prop ID="4" Name="Function" NameU="Function">
						<Value></Value>
						<Label>Fonction</Label>
					</Prop>
					<Prop ID="5" Name="StartDate" NameU="StartDate">
						<Value></Value>
						<Label>Date de début</Label>
					</Prop>
					<Prop ID="6" Name="EndDate" NameU="EndDate">
						<Value></Value>
						<Label>Date de fin</Label>
					</Prop>
					<Prop ID="7" Name="Status" NameU="Status">
						<Value></Value>
						<Label>État</Label>
					</Prop>
				</Shape>
				<Shape ID="5" UniqueID="{28A18DD9-EA14-47C4-A250-390F51C80786}" Name="Lien dynamique.8" NameU="Dynamic connector.8" Master="7">
					<Text>Difficile</Text>
					<XForm>
						<PinX Unit="MM">6.633858267716535</PinX>
						<PinY Unit="MM">6.594488188976379</PinY>
					</XForm>
					<LayerMem>
						<LayerMember>1</LayerMember>
					</LayerMem>
				</Shape>
				<Shape ID="6" UniqueID="{9972A7EE-6238-47EF-8FAD-BCA9C060C716}" Name="Processus.7" NameU="Process.7" Master="6">
					<Text>Choix de la carte «difficile»</Text>
					<XForm>
						<PinX Unit="MM">7.421259842519684</PinX>
						<PinY Unit="MM">6.594488188976378</PinY>
					</XForm>
					<LayerMem>
						<LayerMember>0</LayerMember>
					</LayerMem>
					<Prop ID="1" Name="Cost" NameU="Cost">
						<Value></Value>
						<Label>Coût</Label>
					</Prop>
					<Prop ID="2" Name="ProcessNumber" NameU="ProcessNumber">
						<Value></Value>
						<Label>Numéro de processus</Label>
					</Prop>
					<Prop ID="3" Name="Owner" NameU="Owner">
						<Value></Value>
						<Label>Propriétaire</Label>
					</Prop>
					<Prop ID="4" Name="Function" NameU="Function">
						<Value></Value>
						<Label>Fonction</Label>
					</Prop>
					<Prop ID="5" Name="StartDate" NameU="StartDate">
						<Value></Value>
						<Label>Date de début</Label>
					</Prop>
					<Prop ID="6" Name="EndDate" NameU="EndDate">
						<Value></Value>
						<Label>Date de fin</Label>
					</Prop>
					<Prop ID="7" Name="Status" NameU="Status">
						<Value></Value>
						<Label>État</Label>
					</Prop>
				</Shape>
				<Shape ID="7" UniqueID="{81E70EFC-F4B3-4929-9601-510CD47FF770}" Name="Lien dynamique.10" NameU="Dynamic connector.10" Master="7">
					<Text>Moyen</Text>
					<XForm>
						<PinX Unit="MM">5.846456692913385</PinX>
						<PinY Unit="MM">6.003937007874015</PinY>
					</XForm>
					<LayerMem>
						<LayerMember>1</LayerMember>
					</LayerMem>
				</Shape>
				<Shape ID="8" UniqueID="{E6AB41DE-D2B4-4C62-A4CB-A04E2833791F}" Name="Processus.9" NameU="Process.9" Master="6">
					<Text>Choix de la carte «moyenne»</Text>
					<XForm>
						<PinX Unit="MM">5.846456692913385</PinX>
						<PinY Unit="MM">5.413385826771653</PinY>
					</XForm>
					<LayerMem>
						<LayerMember>0</LayerMember>
					</LayerMem>
					<Prop ID="1" Name="Cost" NameU="Cost">
						<Value></Value>
						<Label>Coût</Label>
					</Prop>
					<Prop ID="2" Name="ProcessNumber" NameU="ProcessNumber">
						<Value></Value>
						<Label>Numéro de processus</Label>
					</Prop>
					<Prop ID="3" Name="Owner" NameU="Owner">
						<Value></Value>
						<Label>Propriétaire</Label>
					</Prop>
					<Prop ID="4" Name="Function" NameU="Function">
						<Value></Value>
						<Label>Fonction</Label>
					</Prop>
					<Prop ID="5" Name="StartDate" NameU="StartDate">
						<Value></Value>
						<Label>Date de début</Label>
					</Prop>
					<Prop ID="6" Name="EndDate" NameU="EndDate">
						<Value></Value>
						<Label>Date de fin</Label>
					</Prop>
					<Prop ID="7" Name="Status" NameU="Status">
						<Value></Value>
						<Label>État</Label>
					</Prop>
				</Shape>
				<Shape ID="9" UniqueID="{5A48E3C8-1C8B-4C27-9639-3508A43E7DB8}" Name="Lien dynamique" NameU="Dynamic connector" Master="7">
					<XForm>
						<PinX Unit="MM">5.846456692913385</PinX>
						<PinY Unit="MM">7.185039370078741</PinY>
					</XForm>
					<LayerMem>
						<LayerMember>1</LayerMember>
					</LayerMem>
				</Shape>
				<Shape ID="11" UniqueID="{0E19A004-1B95-4577-8173-8B72502DDCC6}" Name="Lien dynamique.11" NameU="Dynamic connector.11" Master="7">
					<XForm>
						<PinX Unit="MM">5.059055118110235</PinX>
						<PinY Unit="MM">5.413385826771652</PinY>
					</XForm>
					<LayerMem>
						<LayerMember>1</LayerMember>
					</LayerMem>
				</Shape>
				<Shape ID="10" UniqueID="{C7D04BD6-FB65-419D-A820-FB208DE85D82}" Name="Processus.10" NameU="Process.10" Master="6">
					<Text>Le joueur choisit ses portes</Text>
					<XForm>
						<PinX Unit="MM">5.846456692913385</PinX>
						<PinY Unit="MM">4.232283464566926</PinY>
					</XForm>
					<LayerMem>
						<LayerMember>0</LayerMember>
					</LayerMem>
					<Prop ID="1" Name="Cost" NameU="Cost">
						<Value></Value>
						<Label>Coût</Label>
					</Prop>
					<Prop ID="2" Name="ProcessNumber" NameU="ProcessNumber">
						<Value></Value>
						<Label>Numéro de processus</Label>
					</Prop>
					<Prop ID="3" Name="Owner" NameU="Owner">
						<Value></Value>
						<Label>Propriétaire</Label>
					</Prop>
					<Prop ID="4" Name="Function" NameU="Function">
						<Value></Value>
						<Label>Fonction</Label>
					</Prop>
					<Prop ID="5" Name="StartDate" NameU="StartDate">
						<Value></Value>
						<Label>Date de début</Label>
					</Prop>
					<Prop ID="6" Name="EndDate" NameU="EndDate">
						<Value></Value>
						<Label>Date de fin</Label>
					</Prop>
					<Prop ID="7" Name="Status" NameU="Status">
						<Value></Value>
						<Label>État</Label>
					</Prop>
				</Shape>
				<Shape ID="12" UniqueID="{05E49209-052E-4B71-94E0-296554B270A3}" Name="Lien dynamique.12" NameU="Dynamic connector.12" Master="7">
					<XForm>
						<PinX Unit="MM">5.846456692913385</PinX>
						<PinY Unit="MM">4.822834645669289</PinY>
					</XForm>
					<LayerMem>
						<LayerMember>1</LayerMember>
					</LayerMem>
				</Shape>
				<Shape ID="13" UniqueID="{8F377B18-76F2-4E7E-B3A7-1097C5BFF4BA}" Name="Lien dynamique.13" NameU="Dynamic connector.13" Master="7">
					<XForm>
						<PinX Unit="MM">6.633858267716535</PinX>
						<PinY Unit="MM">5.413385826771652</PinY>
					</XForm>
					<LayerMem>
						<LayerMember>1</LayerMember>
					</LayerMem>
				</Shape>
				<Shape ID="14" UniqueID="{7BF04F12-3B4A-49EE-A6FF-90CA36481A1D}" Name="Sous-processus" NameU="Subprocess" Master="13">
					<Text>Play</Text>
					<XForm>
						<PinX Unit="MM">5.846456692913385</PinX>
						<PinY Unit="MM">2.066929133858268</PinY>
					</XForm>
					<LayerMem>
						<LayerMember>0</LayerMember>
					</LayerMem>
					<Prop ID="1" Name="Cost" NameU="Cost">
						<Value></Value>
						<Label>Coût</Label>
					</Prop>
					<Prop ID="2" Name="ProcessNumber" NameU="ProcessNumber">
						<Value></Value>
						<Label>Numéro de processus</Label>
					</Prop>
					<Prop ID="3" Name="Owner" NameU="Owner">
						<Value></Value>
						<Label>Propriétaire</Label>
					</Prop>
					<Prop ID="4" Name="Function" NameU="Function">
						<Value></Value>
						<Label>Fonction</Label>
					</Prop>
					<Prop ID="5" Name="StartDate" NameU="StartDate">
						<Value></Value>
						<Label>Date de début</Label>
					</Prop>
					<Prop ID="6" Name="EndDate" NameU="EndDate">
						<Value></Value>
						<Label>Date de fin</Label>
					</Prop>
					<Prop ID="7" Name="Status" NameU="Status">
						<Value></Value>
						<Label>État</Label>
					</Prop>
				</Shape>
				<Shape ID="15" UniqueID="{995EC9E8-BC8D-4A1C-AF5A-8D354A117019}" Name="Début/fin.15" NameU="Start/End.15" Master="2">
					<Text>Fin</Text>
					<XForm>
						<PinX Unit="MM">5.846456692913385</PinX>
						<PinY Unit="MM">1.181102362204725</PinY>
					</XForm>
					<LayerMem>
						<LayerMember>0</LayerMember>
					</LayerMem>
					<Prop ID="1" Name="Cost" NameU="Cost">
						<Value></Value>
						<Label>Coût</Label>
					</Prop>
					<Prop ID="2" Name="ProcessNumber" NameU="ProcessNumber">
						<Value></Value>
						<Label>Numéro de processus</Label>
					</Prop>
					<Prop ID="3" Name="Owner" NameU="Owner">
						<Value></Value>
						<Label>Propriétaire</Label>
					</Prop>
					<Prop ID="4" Name="Function" NameU="Function">
						<Value></Value>
						<Label>Fonction</Label>
					</Prop>
					<Prop ID="5" Name="StartDate" NameU="StartDate">
						<Value></Value>
						<Label>Date de début</Label>
					</Prop>
					<Prop ID="6" Name="EndDate" NameU="EndDate">
						<Value></Value>
						<Label>Date de fin</Label>
					</Prop>
					<Prop ID="7" Name="Status" NameU="Status">
						<Value></Value>
						<Label>État</Label>
					</Prop>
				</Shape>
				<Shape ID="17" UniqueID="{EAAAFA18-BD91-4299-B0A1-3B7FFF590471}" Name="Lien dynamique.17" NameU="Dynamic connector.17" Master="7">
					<XForm>
						<PinX Unit="MM">5.846456692913385</PinX>
						<PinY Unit="MM">3.641732283464564</PinY>
					</XForm>
					<LayerMem>
						<LayerMember>1</LayerMember>
					</LayerMem>
				</Shape>
				<Shape ID="16" UniqueID="{0475CAAC-042C-47EC-B439-AAE6F8ED1FBF}" Name="Processus.16" NameU="Process.16" Master="6">
					<Text>Le joueur confirme ca carte</Text>
					<XForm>
						<PinX Unit="MM">5.846456692913385</PinX>
						<PinY Unit="MM">3.051181102362201</PinY>
					</XForm>
					<LayerMem>
						<LayerMember>0</LayerMember>
					</LayerMem>
					<Prop ID="1" Name="Cost" NameU="Cost">
						<Value></Value>
						<Label>Coût</Label>
					</Prop>
					<Prop ID="2" Name="ProcessNumber" NameU="ProcessNumber">
						<Value></Value>
						<Label>Numéro de processus</Label>
					</Prop>
					<Prop ID="3" Name="Owner" NameU="Owner">
						<Value></Value>
						<Label>Propriétaire</Label>
					</Prop>
					<Prop ID="4" Name="Function" NameU="Function">
						<Value></Value>
						<Label>Fonction</Label>
					</Prop>
					<Prop ID="5" Name="StartDate" NameU="StartDate">
						<Value></Value>
						<Label>Date de début</Label>
					</Prop>
					<Prop ID="6" Name="EndDate" NameU="EndDate">
						<Value></Value>
						<Label>Date de fin</Label>
					</Prop>
					<Prop ID="7" Name="Status" NameU="Status">
						<Value></Value>
						<Label>État</Label>
					</Prop>
				</Shape>
				<Shape ID="18" UniqueID="{3347DDB2-650F-417D-AB22-E8363B47B71D}" Name="Lien dynamique.18" NameU="Dynamic connector.18" Master="7">
					<XForm>
						<PinX Unit="MM">5.846456692913385</PinX>
						<PinY Unit="MM">2.559055118110234</PinY>
					</XForm>
					<LayerMem>
						<LayerMember>1</LayerMember>
					</LayerMem>
				</Shape>
				<Shape ID="19" UniqueID="{4D380EEA-7223-417C-B799-FE1F1B903492}" Name="Lien dynamique.19" NameU="Dynamic connector.19" Master="7">
					<XForm>
						<PinX Unit="MM">5.846456692913385</PinX>
						<PinY Unit="MM">1.574803149606300</PinY>
					</XForm>
					<LayerMem>
						<LayerMember>1</LayerMember>
					</LayerMem>
				</Shape>
			</Shapes>
		</Page>
		<Page ID="5" Name="PuzzleAléatoire" NameU="PuzzleAléatoire">
			<PageProps>
				<PageScale Unit="MM">0.039370078740157</PageScale>
				<DrawingScale Unit="MM">0.039370078740157</DrawingScale>
			</PageProps>
			<Layer IX="0">
				<Name>Diagramme de flux</Name>
				<NameUniv>Flowchart</NameUniv>
				<Visible>1</Visible>
			</Layer>
			<Layer IX="1">
				<Name>Lien</Name>
				<NameUniv>Connector</NameUniv>
				<Visible>1</Visible>
			</Layer>
			<Shapes>
				<Shape ID="1" UniqueID="{BB85F415-C65B-45D4-9D86-5D2064409750}" Name="Début/fin" NameU="Start/End" Master="2">
					<Text>Début</Text>
					<XForm>
						<PinX Unit="MM">5.846456692913385</PinX>
						<PinY Unit="MM">7.677165354330708</PinY>
					</XForm>
					<LayerMem>
						<LayerMember>0</LayerMember>
					</LayerMem>
					<Prop ID="1" Name="Cost" NameU="Cost">
						<Value></Value>
						<Label>Coût</Label>
					</Prop>
					<Prop ID="2" Name="ProcessNumber" NameU="ProcessNumber">
						<Value></Value>
						<Label>Numéro de processus</Label>
					</Prop>
					<Prop ID="3" Name="Owner" NameU="Owner">
						<Value></Value>
						<Label>Propriétaire</Label>
					</Prop>
					<Prop ID="4" Name="Function" NameU="Function">
						<Value></Value>
						<Label>Fonction</Label>
					</Prop>
					<Prop ID="5" Name="StartDate" NameU="StartDate">
						<Value></Value>
						<Label>Date de début</Label>
					</Prop>
					<Prop ID="6" Name="EndDate" NameU="EndDate">
						<Value></Value>
						<Label>Date de fin</Label>
					</Prop>
					<Prop ID="7" Name="Status" NameU="Status">
						<Value></Value>
						<Label>État</Label>
					</Prop>
				</Shape>
				<Shape ID="3" UniqueID="{DE9353F8-7201-4610-8413-2F95DA6D63D5}" Name="Lien dynamique" NameU="Dynamic connector" Master="7">
					<XForm>
						<PinX Unit="MM">5.846456692913385</PinX>
						<PinY Unit="MM">7.185039370078740</PinY>
					</XForm>
					<LayerMem>
						<LayerMember>1</LayerMember>
					</LayerMem>
				</Shape>
				<Shape ID="2" UniqueID="{652059FE-FA74-4AE5-A20D-86123218E8F0}" Name="Décision" NameU="Decision" Master="5">
					<Text>Niveau de difficulté </Text>
					<XForm>
						<PinX Unit="MM">5.846456692913385</PinX>
						<PinY Unit="MM">6.594488188976379</PinY>
					</XForm>
					<LayerMem>
						<LayerMember>0</LayerMember>
					</LayerMem>
					<Prop ID="1" Name="Cost" NameU="Cost">
						<Value></Value>
						<Label>Coût</Label>
					</Prop>
					<Prop ID="2" Name="ProcessNumber" NameU="ProcessNumber">
						<Value></Value>
						<Label>Numéro de processus</Label>
					</Prop>
					<Prop ID="3" Name="Owner" NameU="Owner">
						<Value></Value>
						<Label>Propriétaire</Label>
					</Prop>
					<Prop ID="4" Name="Function" NameU="Function">
						<Value></Value>
						<Label>Fonction</Label>
					</Prop>
					<Prop ID="5" Name="StartDate" NameU="StartDate">
						<Value></Value>
						<Label>Date de début</Label>
					</Prop>
					<Prop ID="6" Name="EndDate" NameU="EndDate">
						<Value></Value>
						<Label>Date de fin</Label>
					</Prop>
					<Prop ID="7" Name="Status" NameU="Status">
						<Value></Value>
						<Label>État</Label>
					</Prop>
				</Shape>
				<Shape ID="6" UniqueID="{D454A4A7-2DD7-487B-AE34-70B2EBB896F2}" Name="Lien dynamique.6" NameU="Dynamic connector.6" Master="7">
					<Text>Facile</Text>
					<XForm>
						<PinX Unit="MM">5.059055118110235</PinX>
						<PinY Unit="MM">6.594488188976378</PinY>
					</XForm>
					<LayerMem>
						<LayerMember>1</LayerMember>
					</LayerMem>
				</Shape>
				<Shape ID="5" UniqueID="{F8442FD2-2DB2-4F9B-86C9-A2C7338A618D}" Name="Processus" NameU="Process" Master="6">
					<Text>Choix de la carte «facile»</Text>
					<XForm>
						<PinX Unit="MM">4.271653543307086</PinX>
						<PinY Unit="MM">6.594488188976378</PinY>
					</XForm>
					<LayerMem>
						<LayerMember>0</LayerMember>
					</LayerMem>
					<Prop ID="1" Name="Cost" NameU="Cost">
						<Value></Value>
						<Label>Coût</Label>
					</Prop>
					<Prop ID="2" Name="ProcessNumber" NameU="ProcessNumber">
						<Value></Value>
						<Label>Numéro de processus</Label>
					</Prop>
					<Prop ID="3" Name="Owner" NameU="Owner">
						<Value></Value>
						<Label>Propriétaire</Label>
					</Prop>
					<Prop ID="4" Name="Function" NameU="Function">
						<Value></Value>
						<Label>Fonction</Label>
					</Prop>
					<Prop ID="5" Name="StartDate" NameU="StartDate">
						<Value></Value>
						<Label>Date de début</Label>
					</Prop>
					<Prop ID="6" Name="EndDate" NameU="EndDate">
						<Value></Value>
						<Label>Date de fin</Label>
					</Prop>
					<Prop ID="7" Name="Status" NameU="Status">
						<Value></Value>
						<Label>État</Label>
					</Prop>
				</Shape>
				<Shape ID="8" UniqueID="{4D382D83-F5DD-4E90-8405-D0F2B985B4EE}" Name="Lien dynamique.8" NameU="Dynamic connector.8" Master="7">
					<Text>Difficile</Text>
					<XForm>
						<PinX Unit="MM">6.633858267716535</PinX>
						<PinY Unit="MM">6.594488188976378</PinY>
					</XForm>
					<LayerMem>
						<LayerMember>1</LayerMember>
					</LayerMem>
				</Shape>
				<Shape ID="7" UniqueID="{C8B16012-9404-4E0A-A7A9-774A803BCF19}" Name="Processus.7" NameU="Process.7" Master="6">
					<Text>Choix de la carte «difficile»</Text>
					<XForm>
						<PinX Unit="MM">7.421259842519684</PinX>
						<PinY Unit="MM">6.594488188976378</PinY>
					</XForm>
					<LayerMem>
						<LayerMember>0</LayerMember>
					</LayerMem>
					<Prop ID="1" Name="Cost" NameU="Cost">
						<Value></Value>
						<Label>Coût</Label>
					</Prop>
					<Prop ID="2" Name="ProcessNumber" NameU="ProcessNumber">
						<Value></Value>
						<Label>Numéro de processus</Label>
					</Prop>
					<Prop ID="3" Name="Owner" NameU="Owner">
						<Value></Value>
						<Label>Propriétaire</Label>
					</Prop>
					<Prop ID="4" Name="Function" NameU="Function">
						<Value></Value>
						<Label>Fonction</Label>
					</Prop>
					<Prop ID="5" Name="StartDate" NameU="StartDate">
						<Value></Value>
						<Label>Date de début</Label>
					</Prop>
					<Prop ID="6" Name="EndDate" NameU="EndDate">
						<Value></Value>
						<Label>Date de fin</Label>
					</Prop>
					<Prop ID="7" Name="Status" NameU="Status">
						<Value></Value>
						<Label>État</Label>
					</Prop>
				</Shape>
				<Shape ID="10" UniqueID="{3C136E0E-98A4-419F-8243-4B40505DD2DB}" Name="Lien dynamique.10" NameU="Dynamic connector.10" Master="7">
					<Text>Moyen</Text>
					<XForm>
						<PinX Unit="MM">5.846456692913385</PinX>
						<PinY Unit="MM">6.003937007874015</PinY>
					</XForm>
					<LayerMem>
						<LayerMember>1</LayerMember>
					</LayerMem>
				</Shape>
				<Shape ID="9" UniqueID="{0F71115A-1BEF-4AD4-8EDB-05BC1221A489}" Name="Processus.9" NameU="Process.9" Master="6">
					<Text>Choix de la carte «moyenne»</Text>
					<XForm>
						<PinX Unit="MM">5.846456692913385</PinX>
						<PinY Unit="MM">5.413385826771653</PinY>
					</XForm>
					<LayerMem>
						<LayerMember>0</LayerMember>
					</LayerMem>
					<Prop ID="1" Name="Cost" NameU="Cost">
						<Value></Value>
						<Label>Coût</Label>
					</Prop>
					<Prop ID="2" Name="ProcessNumber" NameU="ProcessNumber">
						<Value></Value>
						<Label>Numéro de processus</Label>
					</Prop>
					<Prop ID="3" Name="Owner" NameU="Owner">
						<Value></Value>
						<Label>Propriétaire</Label>
					</Prop>
					<Prop ID="4" Name="Function" NameU="Function">
						<Value></Value>
						<Label>Fonction</Label>
					</Prop>
					<Prop ID="5" Name="StartDate" NameU="StartDate">
						<Value></Value>
						<Label>Date de début</Label>
					</Prop>
					<Prop ID="6" Name="EndDate" NameU="EndDate">
						<Value></Value>
						<Label>Date de fin</Label>
					</Prop>
					<Prop ID="7" Name="Status" NameU="Status">
						<Value></Value>
						<Label>État</Label>
					</Prop>
				</Shape>
				<Shape ID="17" UniqueID="{FD27025E-499C-43A9-AD47-24ACF4EC1A70}" Name="Lien dynamique.17" NameU="Dynamic connector.17" Master="7">
					<XForm>
						<PinX Unit="MM">5.846456692913385</PinX>
						<PinY Unit="MM">4.822834645669289</PinY>
					</XForm>
					<LayerMem>
						<LayerMember>1</LayerMember>
					</LayerMem>
				</Shape>
				<Shape ID="16" UniqueID="{CC3B416F-2211-4765-AFEF-52781D4FEDDF}" Name="Processus.16" NameU="Process.16" Master="6">
					<Text>Random sur toutes les portes logique disponible par rapport à la liste</Text>
					<XForm>
						<PinX Unit="MM">5.846456692913385</PinX>
						<PinY Unit="MM">4.232283464566927</PinY>
					</XForm>
					<LayerMem>
						<LayerMember>0</LayerMember>
					</LayerMem>
					<Prop ID="1" Name="Cost" NameU="Cost">
						<Value></Value>
						<Label>Coût</Label>
					</Prop>
					<Prop ID="2" Name="ProcessNumber" NameU="ProcessNumber">
						<Value></Value>
						<Label>Numéro de processus</Label>
					</Prop>
					<Prop ID="3" Name="Owner" NameU="Owner">
						<Value></Value>
						<Label>Propriétaire</Label>
					</Prop>
					<Prop ID="4" Name="Function" NameU="Function">
						<Value></Value>
						<Label>Fonction</Label>
					</Prop>
					<Prop ID="5" Name="StartDate" NameU="StartDate">
						<Value></Value>
						<Label>Date de début</Label>
					</Prop>
					<Prop ID="6" Name="EndDate" NameU="EndDate">
						<Value></Value>
						<Label>Date de fin</Label>
					</Prop>
					<Prop ID="7" Name="Status" NameU="Status">
						<Value></Value>
						<Label>État</Label>
					</Prop>
				</Shape>
				<Shape ID="18" UniqueID="{3BA1D378-7F53-45C2-A52A-14F0F241E9A5}" Name="Données" NameU="Data" Master="4">
					<Text>Liste des portes logique</Text>
					<XForm>
						<PinX Unit="MM">7.814960629921261</PinX>
						<PinY Unit="MM">4.232283464566926</PinY>
					</XForm>
					<LayerMem>
						<LayerMember>0</LayerMember>
					</LayerMem>
					<Prop ID="1" Name="Cost" NameU="Cost">
						<Value></Value>
						<Label>Coût</Label>
					</Prop>
					<Prop ID="2" Name="ProcessNumber" NameU="ProcessNumber">
						<Value></Value>
						<Label>Numéro de processus</Label>
					</Prop>
					<Prop ID="3" Name="Owner" NameU="Owner">
						<Value></Value>
						<Label>Propriétaire</Label>
					</Prop>
					<Prop ID="4" Name="Function" NameU="Function">
						<Value></Value>
						<Label>Fonction</Label>
					</Prop>
					<Prop ID="5" Name="StartDate" NameU="StartDate">
						<Value></Value>
						<Label>Date de début</Label>
					</Prop>
					<Prop ID="6" Name="EndDate" NameU="EndDate">
						<Value></Value>
						<Label>Date de fin</Label>
					</Prop>
					<Prop ID="7" Name="Status" NameU="Status">
						<Value></Value>
						<Label>État</Label>
					</Prop>
				</Shape>
				<Shape ID="19" UniqueID="{9BAAEA39-5004-42CA-AD7E-332DCFE29533}" Name="Lien dynamique.19" NameU="Dynamic connector.19" Master="7">
					<XForm>
						<PinX Unit="MM">6.830708661417323</PinX>
						<PinY Unit="MM">4.232283464566926</PinY>
					</XForm>
					<LayerMem>
						<LayerMember>1</LayerMember>
					</LayerMem>
				</Shape>
				<Shape ID="22" UniqueID="{C560392C-A9ED-4850-A72E-E5EF0183FAA0}" Name="Lien dynamique.22" NameU="Dynamic connector.22" Master="7">
					<XForm>
						<PinX Unit="MM">5.059055118110235</PinX>
						<PinY Unit="MM">5.413385826771652</PinY>
					</XForm>
					<LayerMem>
						<LayerMember>1</LayerMember>
					</LayerMem>
				</Shape>
				<Shape ID="23" UniqueID="{7DF34558-6DE8-41E8-8712-A44F8259CA01}" Name="Lien dynamique.23" NameU="Dynamic connector.23" Master="7">
					<XForm>
						<PinX Unit="MM">6.633858267716535</PinX>
						<PinY Unit="MM">5.413385826771652</PinY>
					</XForm>
					<LayerMem>
						<LayerMember>1</LayerMember>
					</LayerMem>
				</Shape>
				<Shape ID="26" UniqueID="{FF95D227-DB07-4F4A-8AD4-FF7F816824B2}" Name="Sous-processus" NameU="Subprocess" Master="13">
					<Text>Play</Text>
					<XForm>
						<PinX Unit="MM">5.846456692913385</PinX>
						<PinY Unit="MM">3.051181102362202</PinY>
					</XForm>
					<LayerMem>
						<LayerMember>0</LayerMember>
					</LayerMem>
					<Prop ID="1" Name="Cost" NameU="Cost">
						<Value></Value>
						<Label>Coût</Label>
					</Prop>
					<Prop ID="2" Name="ProcessNumber" NameU="ProcessNumber">
						<Value></Value>
						<Label>Numéro de processus</Label>
					</Prop>
					<Prop ID="3" Name="Owner" NameU="Owner">
						<Value></Value>
						<Label>Propriétaire</Label>
					</Prop>
					<Prop ID="4" Name="Function" NameU="Function">
						<Value></Value>
						<Label>Fonction</Label>
					</Prop>
					<Prop ID="5" Name="StartDate" NameU="StartDate">
						<Value></Value>
						<Label>Date de début</Label>
					</Prop>
					<Prop ID="6" Name="EndDate" NameU="EndDate">
						<Value></Value>
						<Label>Date de fin</Label>
					</Prop>
					<Prop ID="7" Name="Status" NameU="Status">
						<Value></Value>
						<Label>État</Label>
					</Prop>
				</Shape>
				<Shape ID="27" UniqueID="{66EC3373-810C-45CF-BB61-B8DF31E3E5AB}" Name="Lien dynamique.27" NameU="Dynamic connector.27" Master="7">
					<XForm>
						<PinX Unit="MM">5.846456692913385</PinX>
						<PinY Unit="MM">3.641732283464564</PinY>
					</XForm>
					<LayerMem>
						<LayerMember>1</LayerMember>
					</LayerMem>
				</Shape>
				<Shape ID="29" UniqueID="{E4CD46AE-8367-4953-B8CF-392C33E450C4}" Name="Lien dynamique.29" NameU="Dynamic connector.29" Master="7">
					<XForm>
						<PinX Unit="MM">5.846456692913385</PinX>
						<PinY Unit="MM">2.460629921259840</PinY>
					</XForm>
					<LayerMem>
						<LayerMember>1</LayerMember>
					</LayerMem>
				</Shape>
				<Shape ID="28" UniqueID="{37A994C8-78B9-4C63-AD8C-6FF3827F43FF}" Name="Début/fin.28" NameU="Start/End.28" Master="2">
					<Text>FIn</Text>
					<XForm>
						<PinX Unit="MM">5.846456692913385</PinX>
						<PinY Unit="MM">1.968503937007871</PinY>
					</XForm>
					<LayerMem>
						<LayerMember>0</LayerMember>
					</LayerMem>
					<Prop ID="1" Name="Cost" NameU="Cost">
						<Value></Value>
						<Label>Coût</Label>
					</Prop>
					<Prop ID="2" Name="ProcessNumber" NameU="ProcessNumber">
						<Value></Value>
						<Label>Numéro de processus</Label>
					</Prop>
					<Prop ID="3" Name="Owner" NameU="Owner">
						<Value></Value>
						<Label>Propriétaire</Label>
					</Prop>
					<Prop ID="4" Name="Function" NameU="Function">
						<Value></Value>
						<Label>Fonction</Label>
					</Prop>
					<Prop ID="5" Name="StartDate" NameU="StartDate">
						<Value></Value>
						<Label>Date de début</Label>
					</Prop>
					<Prop ID="6" Name="EndDate" NameU="EndDate">
						<Value></Value>
						<Label>Date de fin</Label>
					</Prop>
					<Prop ID="7" Name="Status" NameU="Status">
						<Value></Value>
						<Label>État</Label>
					</Prop>
				</Shape>
			</Shapes>
		</Page>
		<Page ID="8" Name="Play" NameU="Play">
			<PageProps>
				<PageScale Unit="MM">0.039370078740157</PageScale>
				<DrawingScale Unit="MM">0.039370078740157</DrawingScale>
			</PageProps>
			<Layer IX="0">
				<Name>Diagramme de flux</Name>
				<NameUniv>Flowchart</NameUniv>
				<Visible>1</Visible>
			</Layer>
			<Layer IX="1">
				<Name>Lien</Name>
				<NameUniv>Connector</NameUniv>
				<Visible>1</Visible>
			</Layer>
			<Shapes>
				<Shape ID="1" UniqueID="{51C9B9B0-9B2D-4881-98CD-B0F547998254}" Name="Début/fin" NameU="Start/End" Master="2">
					<Text>Début</Text>
					<XForm>
						<PinX Unit="MM">5.846456692913385</PinX>
						<PinY Unit="MM">7.677165354330707</PinY>
					</XForm>
					<LayerMem>
						<LayerMember>0</LayerMember>
					</LayerMem>
					<Prop ID="1" Name="Cost" NameU="Cost">
						<Value></Value>
						<Label>Coût</Label>
					</Prop>
					<Prop ID="2" Name="ProcessNumber" NameU="ProcessNumber">
						<Value></Value>
						<Label>Numéro de processus</Label>
					</Prop>
					<Prop ID="3" Name="Owner" NameU="Owner">
						<Value></Value>
						<Label>Propriétaire</Label>
					</Prop>
					<Prop ID="4" Name="Function" NameU="Function">
						<Value></Value>
						<Label>Fonction</Label>
					</Prop>
					<Prop ID="5" Name="StartDate" NameU="StartDate">
						<Value></Value>
						<Label>Date de début</Label>
					</Prop>
					<Prop ID="6" Name="EndDate" NameU="EndDate">
						<Value></Value>
						<Label>Date de fin</Label>
					</Prop>
					<Prop ID="7" Name="Status" NameU="Status">
						<Value></Value>
						<Label>État</Label>
					</Prop>
				</Shape>
				<Shape ID="7" UniqueID="{8A74D6ED-F93D-43C1-89F1-1CBD9AA5D7FF}" Name="Lien dynamique" NameU="Dynamic connector" Master="7">
					<XForm>
						<PinX Unit="MM">5.846456692913385</PinX>
						<PinY Unit="MM">7.185039370078739</PinY>
					</XForm>
					<LayerMem>
						<LayerMember>1</LayerMember>
					</LayerMem>
				</Shape>
				<Shape ID="6" UniqueID="{A00495E5-4E50-4510-9A9C-2898314B25C1}" Name="Sous-processus" NameU="Subprocess" Master="13">
					<Text>Affichage Théorie</Text>
					<XForm>
						<PinX Unit="MM">5.846456692913385</PinX>
						<PinY Unit="MM">6.594488188976377</PinY>
					</XForm>
					<LayerMem>
						<LayerMember>0</LayerMember>
					</LayerMem>
					<Prop ID="1" Name="Cost" NameU="Cost">
						<Value></Value>
						<Label>Coût</Label>
					</Prop>
					<Prop ID="2" Name="ProcessNumber" NameU="ProcessNumber">
						<Value></Value>
						<Label>Numéro de processus</Label>
					</Prop>
					<Prop ID="3" Name="Owner" NameU="Owner">
						<Value></Value>
						<Label>Propriétaire</Label>
					</Prop>
					<Prop ID="4" Name="Function" NameU="Function">
						<Value></Value>
						<Label>Fonction</Label>
					</Prop>
					<Prop ID="5" Name="StartDate" NameU="StartDate">
						<Value></Value>
						<Label>Date de début</Label>
					</Prop>
					<Prop ID="6" Name="EndDate" NameU="EndDate">
						<Value></Value>
						<Label>Date de fin</Label>
					</Prop>
					<Prop ID="7" Name="Status" NameU="Status">
						<Value></Value>
						<Label>État</Label>
					</Prop>
				</Shape>
				<Shape ID="10" UniqueID="{5DC6C1C5-29AD-41A3-A5D1-C8BE07DDF23C}" Name="Lien dynamique.10" NameU="Dynamic connector.10" Master="7">
					<XForm>
						<PinX Unit="MM">5.846456692913385</PinX>
						<PinY Unit="MM">6.003937007874013</PinY>
					</XForm>
					<LayerMem>
						<LayerMember>1</LayerMember>
					</LayerMem>
				</Shape>
				<Shape ID="9" UniqueID="{BEF4619F-0C3E-4D10-9BF0-A1AADF32730D}" Name="Décision" NameU="Decision" Master="5">
					<Text>Appuie sure F1 ?</Text>
					<XForm>
						<PinX Unit="MM">5.846456692913385</PinX>
						<PinY Unit="MM">5.413385826771651</PinY>
					</XForm>
					<LayerMem>
						<LayerMember>0</LayerMember>
					</LayerMem>
					<Prop ID="1" Name="Cost" NameU="Cost">
						<Value></Value>
						<Label>Coût</Label>
					</Prop>
					<Prop ID="2" Name="ProcessNumber" NameU="ProcessNumber">
						<Value></Value>
						<Label>Numéro de processus</Label>
					</Prop>
					<Prop ID="3" Name="Owner" NameU="Owner">
						<Value></Value>
						<Label>Propriétaire</Label>
					</Prop>
					<Prop ID="4" Name="Function" NameU="Function">
						<Value></Value>
						<Label>Fonction</Label>
					</Prop>
					<Prop ID="5" Name="StartDate" NameU="StartDate">
						<Value></Value>
						<Label>Date de début</Label>
					</Prop>
					<Prop ID="6" Name="EndDate" NameU="EndDate">
						<Value></Value>
						<Label>Date de fin</Label>
					</Prop>
					<Prop ID="7" Name="Status" NameU="Status">
						<Value></Value>
						<Label>État</Label>
					</Prop>
				</Shape>
				<Shape ID="12" UniqueID="{8437D413-F350-45D1-90A4-275778AA6986}" Name="Lien dynamique.12" NameU="Dynamic connector.12" Master="7">
					<Text>Oui</Text>
					<XForm>
						<PinX Unit="MM">6.092519685039369</PinX>
						<PinY Unit="MM">6.151574803149604</PinY>
					</XForm>
					<LayerMem>
						<LayerMember>1</LayerMember>
					</LayerMem>
				</Shape>
				<Shape ID="15" UniqueID="{653BFDC6-B7F2-4551-8552-BDA1D974FB60}" Name="Lien dynamique.15" NameU="Dynamic connector.15" Master="7">
					<Text>Non</Text>
					<XForm>
						<PinX Unit="MM">5.846456692913385</PinX>
						<PinY Unit="MM">4.822834645669288</PinY>
					</XForm>
					<LayerMem>
						<LayerMember>1</LayerMember>
					</LayerMem>
				</Shape>
				<Shape ID="14" UniqueID="{7854CA9E-D0AE-4973-8E22-35E9F261A0D7}" Name="Processus" NameU="Process" Master="6">
					<Text>Le jeu est affiché</Text>
					<XForm>
						<PinX Unit="MM">5.846456692913385</PinX>
						<PinY Unit="MM">4.232283464566925</PinY>
					</XForm>
					<LayerMem>
						<LayerMember>0</LayerMember>
					</LayerMem>
					<Prop ID="1" Name="Cost" NameU="Cost">
						<Value></Value>
						<Label>Coût</Label>
					</Prop>
					<Prop ID="2" Name="ProcessNumber" NameU="ProcessNumber">
						<Value></Value>
						<Label>Numéro de processus</Label>
					</Prop>
					<Prop ID="3" Name="Owner" NameU="Owner">
						<Value></Value>
						<Label>Propriétaire</Label>
					</Prop>
					<Prop ID="4" Name="Function" NameU="Function">
						<Value></Value>
						<Label>Fonction</Label>
					</Prop>
					<Prop ID="5" Name="StartDate" NameU="StartDate">
						<Value></Value>
						<Label>Date de début</Label>
					</Prop>
					<Prop ID="6" Name="EndDate" NameU="EndDate">
						<Value></Value>
						<Label>Date de fin</Label>
					</Prop>
					<Prop ID="7" Name="Status" NameU="Status">
						<Value></Value>
						<Label>État</Label>
					</Prop>
				</Shape>
				<Shape ID="19" UniqueID="{C87052C0-724E-409D-8C7D-1C6420D4A3F7}" Name="Lien dynamique.19" NameU="Dynamic connector.19" Master="7">
					<XForm>
						<PinX Unit="MM">5.846456692913385</PinX>
						<PinY Unit="MM">3.651574803149602</PinY>
					</XForm>
					<LayerMem>
						<LayerMember>1</LayerMember>
					</LayerMem>
				</Shape>
				<Shape ID="18" UniqueID="{99D88D8F-DA1D-4BA5-B73E-97A5597ABE7B}" Name="Décision.18" NameU="Decision.18" Master="5">
					<Text>Le joueur donne la bonne réponse</Text>
					<XForm>
						<PinX Unit="MM">5.846456692913385</PinX>
						<PinY Unit="MM">3.051181102362200</PinY>
					</XForm>
					<LayerMem>
						<LayerMember>0</LayerMember>
					</LayerMem>
					<Prop ID="1" Name="Cost" NameU="Cost">
						<Value></Value>
						<Label>Coût</Label>
					</Prop>
					<Prop ID="2" Name="ProcessNumber" NameU="ProcessNumber">
						<Value></Value>
						<Label>Numéro de processus</Label>
					</Prop>
					<Prop ID="3" Name="Owner" NameU="Owner">
						<Value></Value>
						<Label>Propriétaire</Label>
					</Prop>
					<Prop ID="4" Name="Function" NameU="Function">
						<Value></Value>
						<Label>Fonction</Label>
					</Prop>
					<Prop ID="5" Name="StartDate" NameU="StartDate">
						<Value></Value>
						<Label>Date de début</Label>
					</Prop>
					<Prop ID="6" Name="EndDate" NameU="EndDate">
						<Value></Value>
						<Label>Date de fin</Label>
					</Prop>
					<Prop ID="7" Name="Status" NameU="Status">
						<Value></Value>
						<Label>État</Label>
					</Prop>
				</Shape>
				<Shape ID="20" UniqueID="{E7DFD5C8-7C90-4703-ABA8-F2D98D398F53}" Name="Lien dynamique.20" NameU="Dynamic connector.20" Master="7">
					<Text>Non</Text>
					<XForm>
						<PinX Unit="MM">6.338582677165354</PinX>
						<PinY Unit="MM">3.641732283464563</PinY>
					</XForm>
					<LayerMem>
						<LayerMember>1</LayerMember>
					</LayerMem>
				</Shape>
				<Shape ID="22" UniqueID="{FB07AFDD-3C46-48BC-9D4B-CF5B36DDCF43}" Name="Lien dynamique.22" NameU="Dynamic connector.22" Master="7">
					<Text>Oui</Text>
					<XForm>
						<PinX Unit="MM">5.846456692913385</PinX>
						<PinY Unit="MM">2.440944881889759</PinY>
					</XForm>
					<LayerMem>
						<LayerMember>1</LayerMember>
					</LayerMem>
				</Shape>
				<Shape ID="21" UniqueID="{44D663DF-7BCF-4C63-A812-388FD455CA7C}" Name="Sous-processus.21" NameU="Subprocess.21" Master="13">
					<Text>Affichage Score</Text>
					<XForm>
						<PinX Unit="MM">5.846456692913385</PinX>
						<PinY Unit="MM">1.850393700787397</PinY>
					</XForm>
					<LayerMem>
						<LayerMember>0</LayerMember>
					</LayerMem>
					<Prop ID="1" Name="Cost" NameU="Cost">
						<Value></Value>
						<Label>Coût</Label>
					</Prop>
					<Prop ID="2" Name="ProcessNumber" NameU="ProcessNumber">
						<Value></Value>
						<Label>Numéro de processus</Label>
					</Prop>
					<Prop ID="3" Name="Owner" NameU="Owner">
						<Value></Value>
						<Label>Propriétaire</Label>
					</Prop>
					<Prop ID="4" Name="Function" NameU="Function">
						<Value></Value>
						<Label>Fonction</Label>
					</Prop>
					<Prop ID="5" Name="StartDate" NameU="StartDate">
						<Value></Value>
						<Label>Date de début</Label>
					</Prop>
					<Prop ID="6" Name="EndDate" NameU="EndDate">
						<Value></Value>
						<Label>Date de fin</Label>
					</Prop>
					<Prop ID="7" Name="Status" NameU="Status">
						<Value></Value>
						<Label>État</Label>
					</Prop>
				</Shape>
				<Shape ID="23" UniqueID="{8C8E7E75-52C9-449C-9DC0-AD72F1C835CC}" Name="Début/fin.23" NameU="Start/End.23" Master="2">
					<Text>Fin</Text>
					<XForm>
						<PinX Unit="MM">5.846456692913385</PinX>
						<PinY Unit="MM">0.590551181102362</PinY>
					</XForm>
					<LayerMem>
						<LayerMember>0</LayerMember>
					</LayerMem>
					<Prop ID="1" Name="Cost" NameU="Cost">
						<Value></Value>
						<Label>Coût</Label>
					</Prop>
					<Prop ID="2" Name="ProcessNumber" NameU="ProcessNumber">
						<Value></Value>
						<Label>Numéro de processus</Label>
					</Prop>
					<Prop ID="3" Name="Owner" NameU="Owner">
						<Value></Value>
						<Label>Propriétaire</Label>
					</Prop>
					<Prop ID="4" Name="Function" NameU="Function">
						<Value></Value>
						<Label>Fonction</Label>
					</Prop>
					<Prop ID="5" Name="StartDate" NameU="StartDate">
						<Value></Value>
						<Label>Date de début</Label>
					</Prop>
					<Prop ID="6" Name="EndDate" NameU="EndDate">
						<Value></Value>
						<Label>Date de fin</Label>
					</Prop>
					<Prop ID="7" Name="Status" NameU="Status">
						<Value></Value>
						<Label>État</Label>
					</Prop>
				</Shape>
				<Shape ID="25" UniqueID="{8AD8D24F-3D34-4E8A-91AA-046153B76CA7}" Name="Sous-processus.25" NameU="Subprocess.25" Master="13">
					<Text>Capture d’écran</Text>
					<XForm>
						<PinX Unit="MM">8.661417322834644</PinX>
						<PinY Unit="MM">1.850393700787397</PinY>
					</XForm>
					<LayerMem>
						<LayerMember>0</LayerMember>
					</LayerMem>
					<Prop ID="1" Name="Cost" NameU="Cost">
						<Value></Value>
						<Label>Coût</Label>
					</Prop>
					<Prop ID="2" Name="ProcessNumber" NameU="ProcessNumber">
						<Value></Value>
						<Label>Numéro de processus</Label>
					</Prop>
					<Prop ID="3" Name="Owner" NameU="Owner">
						<Value></Value>
						<Label>Propriétaire</Label>
					</Prop>
					<Prop ID="4" Name="Function" NameU="Function">
						<Value></Value>
						<Label>Fonction</Label>
					</Prop>
					<Prop ID="5" Name="StartDate" NameU="StartDate">
						<Value></Value>
						<Label>Date de début</Label>
					</Prop>
					<Prop ID="6" Name="EndDate" NameU="EndDate">
						<Value></Value>
						<Label>Date de fin</Label>
					</Prop>
					<Prop ID="7" Name="Status" NameU="Status">
						<Value></Value>
						<Label>État</Label>
					</Prop>
				</Shape>
				<Shape ID="26" UniqueID="{C4498600-DF52-4302-A60A-B9268ED9922F}" Name="Décision.26" NameU="Decision.26" Master="5">
					<Text>Capture d’écran ?</Text>
					<XForm>
						<PinX Unit="MM">7.106299212598424</PinX>
						<PinY Unit="MM">1.850393700787397</PinY>
					</XForm>
					<LayerMem>
						<LayerMember>0</LayerMember>
					</LayerMem>
					<Prop ID="1" Name="Cost" NameU="Cost">
						<Value></Value>
						<Label>Coût</Label>
					</Prop>
					<Prop ID="2" Name="ProcessNumber" NameU="ProcessNumber">
						<Value></Value>
						<Label>Numéro de processus</Label>
					</Prop>
					<Prop ID="3" Name="Owner" NameU="Owner">
						<Value></Value>
						<Label>Propriétaire</Label>
					</Prop>
					<Prop ID="4" Name="Function" NameU="Function">
						<Value></Value>
						<Label>Fonction</Label>
					</Prop>
					<Prop ID="5" Name="StartDate" NameU="StartDate">
						<Value></Value>
						<Label>Date de début</Label>
					</Prop>
					<Prop ID="6" Name="EndDate" NameU="EndDate">
						<Value></Value>
						<Label>Date de fin</Label>
					</Prop>
					<Prop ID="7" Name="Status" NameU="Status">
						<Value></Value>
						<Label>État</Label>
					</Prop>
				</Shape>
				<Shape ID="27" UniqueID="{23E8740E-5D15-4CE9-8432-F7EA6CE135EC}" Name="Lien dynamique.27" NameU="Dynamic connector.27" Master="7">
					<XForm>
						<PinX Unit="MM">6.476377952755905</PinX>
						<PinY Unit="MM">1.850393700787397</PinY>
					</XForm>
					<LayerMem>
						<LayerMember>1</LayerMember>
					</LayerMem>
				</Shape>
				<Shape ID="28" UniqueID="{FC55CBAF-E476-4145-AB41-E36EF10A3789}" Name="Lien dynamique.28" NameU="Dynamic connector.28" Master="7">
					<Text>Oui</Text>
					<XForm>
						<PinX Unit="MM">7.883858267716534</PinX>
						<PinY Unit="MM">1.850393700787397</PinY>
					</XForm>
					<LayerMem>
						<LayerMember>1</LayerMember>
					</LayerMem>
				</Shape>
				<Shape ID="29" UniqueID="{17A43AE7-5375-4AB0-A3BE-76E13DA1712F}" Name="Lien dynamique.29" NameU="Dynamic connector.29" Master="7">
					<XForm>
						<PinX Unit="MM">7.499999999999999</PinX>
						<PinY Unit="MM">1.072834645669287</PinY>
					</XForm>
					<LayerMem>
						<LayerMember>1</LayerMember>
					</LayerMem>
				</Shape>
				<Shape ID="30" UniqueID="{4BF3360C-E7A8-4CCF-A69C-7458CDB1C238}" Name="Lien dynamique.30" NameU="Dynamic connector.30" Master="7">
					<Text>Non</Text>
					<XForm>
						<PinX Unit="MM">6.722440944881889</PinX>
						<PinY Unit="MM">1.072834645669287</PinY>
					</XForm>
					<LayerMem>
						<LayerMember>1</LayerMember>
					</LayerMem>
				</Shape>
			</Shapes>
		</Page>
		<Page ID="9" Name="Affichage théorie" NameU="Affichage théorie">
			<PageProps>
				<PageScale Unit="MM">0.039370078740157</PageScale>
				<DrawingScale Unit="MM">0.039370078740157</DrawingScale>
			</PageProps>
			<Layer IX="0">
				<Name>Diagramme de flux</Name>
				<NameUniv>Flowchart</NameUniv>
				<Visible>1</Visible>
			</Layer>
			<Layer IX="1">
				<Name>Lien</Name>
				<NameUniv>Connector</NameUniv>
				<Visible>1</Visible>
			</Layer>
			<Shapes>
				<Shape ID="1" UniqueID="{EAE2D3B5-1AA1-402B-8442-E2AFA726AD4D}" Name="Début/fin" NameU="Start/End" Master="2">
					<Text>Début</Text>
					<XForm>
						<PinX Unit="MM">5.846456692913385</PinX>
						<PinY Unit="MM">7.677165354330707</PinY>
					</XForm>
					<LayerMem>
						<LayerMember>0</LayerMember>
					</LayerMem>
					<Prop ID="1" Name="Cost" NameU="Cost">
						<Value></Value>
						<Label>Coût</Label>
					</Prop>
					<Prop ID="2" Name="ProcessNumber" NameU="ProcessNumber">
						<Value></Value>
						<Label>Numéro de processus</Label>
					</Prop>
					<Prop ID="3" Name="Owner" NameU="Owner">
						<Value></Value>
						<Label>Propriétaire</Label>
					</Prop>
					<Prop ID="4" Name="Function" NameU="Function">
						<Value></Value>
						<Label>Fonction</Label>
					</Prop>
					<Prop ID="5" Name="StartDate" NameU="StartDate">
						<Value></Value>
						<Label>Date de début</Label>
					</Prop>
					<Prop ID="6" Name="EndDate" NameU="EndDate">
						<Value></Value>
						<Label>Date de fin</Label>
					</Prop>
					<Prop ID="7" Name="Status" NameU="Status">
						<Value></Value>
						<Label>État</Label>
					</Prop>
				</Shape>
				<Shape ID="4" UniqueID="{4985DBEB-F429-4A64-B932-B501001F6695}" Name="Lien dynamique" NameU="Dynamic connector" Master="7">
					<XForm>
						<PinX Unit="MM">5.846456692913385</PinX>
						<PinY Unit="MM">7.185039370078739</PinY>
					</XForm>
					<LayerMem>
						<LayerMember>1</LayerMember>
					</LayerMem>
				</Shape>
				<Shape ID="3" UniqueID="{5537E0C6-B9B5-4053-894A-D9DECF52843D}" Name="Processus" NameU="Process" Master="6">
					<Text>Récupération des portes actives</Text>
					<XForm>
						<PinX Unit="MM">5.846456692913385</PinX>
						<PinY Unit="MM">6.594488188976377</PinY>
					</XForm>
					<LayerMem>
						<LayerMember>0</LayerMember>
					</LayerMem>
					<Prop ID="1" Name="Cost" NameU="Cost">
						<Value></Value>
						<Label>Coût</Label>
					</Prop>
					<Prop ID="2" Name="ProcessNumber" NameU="ProcessNumber">
						<Value></Value>
						<Label>Numéro de processus</Label>
					</Prop>
					<Prop ID="3" Name="Owner" NameU="Owner">
						<Value></Value>
						<Label>Propriétaire</Label>
					</Prop>
					<Prop ID="4" Name="Function" NameU="Function">
						<Value></Value>
						<Label>Fonction</Label>
					</Prop>
					<Prop ID="5" Name="StartDate" NameU="StartDate">
						<Value></Value>
						<Label>Date de début</Label>
					</Prop>
					<Prop ID="6" Name="EndDate" NameU="EndDate">
						<Value></Value>
						<Label>Date de fin</Label>
					</Prop>
					<Prop ID="7" Name="Status" NameU="Status">
						<Value></Value>
						<Label>État</Label>
					</Prop>
				</Shape>
				<Shape ID="5" UniqueID="{63BA3CFA-3965-4470-8C14-461F00B15F7D}" Name="Données" NameU="Data" Master="4">
					<Text>Liste des théories</Text>
					<XForm>
						<PinX Unit="MM">7.421259842519684</PinX>
						<PinY Unit="MM">5.413385826771651</PinY>
					</XForm>
					<LayerMem>
						<LayerMember>0</LayerMember>
					</LayerMem>
					<Prop ID="1" Name="Cost" NameU="Cost">
						<Value></Value>
						<Label>Coût</Label>
					</Prop>
					<Prop ID="2" Name="ProcessNumber" NameU="ProcessNumber">
						<Value></Value>
						<Label>Numéro de processus</Label>
					</Prop>
					<Prop ID="3" Name="Owner" NameU="Owner">
						<Value></Value>
						<Label>Propriétaire</Label>
					</Prop>
					<Prop ID="4" Name="Function" NameU="Function">
						<Value></Value>
						<Label>Fonction</Label>
					</Prop>
					<Prop ID="5" Name="StartDate" NameU="StartDate">
						<Value></Value>
						<Label>Date de début</Label>
					</Prop>
					<Prop ID="6" Name="EndDate" NameU="EndDate">
						<Value></Value>
						<Label>Date de fin</Label>
					</Prop>
					<Prop ID="7" Name="Status" NameU="Status">
						<Value></Value>
						<Label>État</Label>
					</Prop>
				</Shape>
				<Shape ID="8" UniqueID="{9C434396-2036-4A8D-A7F6-38E770CE64A7}" Name="Lien dynamique.8" NameU="Dynamic connector.8" Master="7">
					<XForm>
						<PinX Unit="MM">5.846456692913385</PinX>
						<PinY Unit="MM">6.003937007874013</PinY>
					</XForm>
					<LayerMem>
						<LayerMember>1</LayerMember>
					</LayerMem>
				</Shape>
				<Shape ID="7" UniqueID="{F3ACA9A3-25E9-4148-B383-FFA0DE5E4445}" Name="Processus.7" NameU="Process.7" Master="6">
					<Text>Affiche les théories avec la liste</Text>
					<XForm>
						<PinX Unit="MM">5.846456692913385</PinX>
						<PinY Unit="MM">5.413385826771651</PinY>
					</XForm>
					<LayerMem>
						<LayerMember>0</LayerMember>
					</LayerMem>
					<Prop ID="1" Name="Cost" NameU="Cost">
						<Value></Value>
						<Label>Coût</Label>
					</Prop>
					<Prop ID="2" Name="ProcessNumber" NameU="ProcessNumber">
						<Value></Value>
						<Label>Numéro de processus</Label>
					</Prop>
					<Prop ID="3" Name="Owner" NameU="Owner">
						<Value></Value>
						<Label>Propriétaire</Label>
					</Prop>
					<Prop ID="4" Name="Function" NameU="Function">
						<Value></Value>
						<Label>Fonction</Label>
					</Prop>
					<Prop ID="5" Name="StartDate" NameU="StartDate">
						<Value></Value>
						<Label>Date de début</Label>
					</Prop>
					<Prop ID="6" Name="EndDate" NameU="EndDate">
						<Value></Value>
						<Label>Date de fin</Label>
					</Prop>
					<Prop ID="7" Name="Status" NameU="Status">
						<Value></Value>
						<Label>État</Label>
					</Prop>
				</Shape>
				<Shape ID="9" UniqueID="{FB2D3297-72B2-4BBA-B32D-2B01FA624164}" Name="Lien dynamique.9" NameU="Dynamic connector.9" Master="7">
					<XForm>
						<PinX Unit="MM">6.633858267716535</PinX>
						<PinY Unit="MM">5.413385826771650</PinY>
					</XForm>
					<LayerMem>
						<LayerMember>1</LayerMember>
					</LayerMem>
				</Shape>
				<Shape ID="11" UniqueID="{E3E95B3D-7048-4AAF-BBA7-B3BB16FC5EA5}" Name="Lien dynamique.11" NameU="Dynamic connector.11" Master="7">
					<XForm>
						<PinX Unit="MM">5.846456692913385</PinX>
						<PinY Unit="MM">4.822834645669288</PinY>
					</XForm>
					<LayerMem>
						<LayerMember>1</LayerMember>
					</LayerMem>
				</Shape>
				<Shape ID="10" UniqueID="{D7300298-3D86-4CB9-AF84-18D294D74404}" Name="Début/fin.10" NameU="Start/End.10" Master="2">
					<Text>Fin</Text>
					<XForm>
						<PinX Unit="MM">5.846456692913385</PinX>
						<PinY Unit="MM">4.330708661417320</PinY>
					</XForm>
					<LayerMem>
						<LayerMember>0</LayerMember>
					</LayerMem>
					<Prop ID="1" Name="Cost" NameU="Cost">
						<Value></Value>
						<Label>Coût</Label>
					</Prop>
					<Prop ID="2" Name="ProcessNumber" NameU="ProcessNumber">
						<Value></Value>
						<Label>Numéro de processus</Label>
					</Prop>
					<Prop ID="3" Name="Owner" NameU="Owner">
						<Value></Value>
						<Label>Propriétaire</Label>
					</Prop>
					<Prop ID="4" Name="Function" NameU="Function">
						<Value></Value>
						<Label>Fonction</Label>
					</Prop>
					<Prop ID="5" Name="StartDate" NameU="StartDate">
						<Value></Value>
						<Label>Date de début</Label>
					</Prop>
					<Prop ID="6" Name="EndDate" NameU="EndDate">
						<Value></Value>
						<Label>Date de fin</Label>
					</Prop>
					<Prop ID="7" Name="Status" NameU="Status">
						<Value></Value>
						<Label>État</Label>
					</Prop>
				</Shape>
			</Shapes>
		</Page>
		<Page ID="10" Name="Affichage scores" NameU="Affichage scores">
			<PageProps>
				<PageScale Unit="MM">0.039370078740157</PageScale>
				<DrawingScale Unit="MM">0.039370078740157</DrawingScale>
			</PageProps>
			<Layer IX="0">
				<Name>Diagramme de flux</Name>
				<NameUniv>Flowchart</NameUniv>
				<Visible>1</Visible>
			</Layer>
			<Layer IX="1">
				<Name>Lien</Name>
				<NameUniv>Connector</NameUniv>
				<Visible>1</Visible>
			</Layer>
			<Shapes>
				<Shape ID="1" UniqueID="{BE1546F1-3F07-4219-8B8A-04D18A0D3CDC}" Name="Début/fin" NameU="Start/End" Master="2">
					<Text>Début</Text>
					<XForm>
						<PinX Unit="MM">5.846456692913385</PinX>
						<PinY Unit="MM">7.677165354330707</PinY>
					</XForm>
					<LayerMem>
						<LayerMember>0</LayerMember>
					</LayerMem>
					<Prop ID="1" Name="Cost" NameU="Cost">
						<Value></Value>
						<Label>Coût</Label>
					</Prop>
					<Prop ID="2" Name="ProcessNumber" NameU="ProcessNumber">
						<Value></Value>
						<Label>Numéro de processus</Label>
					</Prop>
					<Prop ID="3" Name="Owner" NameU="Owner">
						<Value></Value>
						<Label>Propriétaire</Label>
					</Prop>
					<Prop ID="4" Name="Function" NameU="Function">
						<Value></Value>
						<Label>Fonction</Label>
					</Prop>
					<Prop ID="5" Name="StartDate" NameU="StartDate">
						<Value></Value>
						<Label>Date de début</Label>
					</Prop>
					<Prop ID="6" Name="EndDate" NameU="EndDate">
						<Value></Value>
						<Label>Date de fin</Label>
					</Prop>
					<Prop ID="7" Name="Status" NameU="Status">
						<Value></Value>
						<Label>État</Label>
					</Prop>
				</Shape>
				<Shape ID="3" UniqueID="{5E650E62-1783-41BF-9E0D-866FC35E9FF0}" Name="Lien dynamique" NameU="Dynamic connector" Master="7">
					<XForm>
						<PinX Unit="MM">5.846456692913385</PinX>
						<PinY Unit="MM">7.185039370078739</PinY>
					</XForm>
					<LayerMem>
						<LayerMember>1</LayerMember>
					</LayerMem>
				</Shape>
				<Shape ID="2" UniqueID="{F0C80758-2B34-4E9A-88E6-C566F363354F}" Name="Processus" NameU="Process" Master="6">
					<Text>Récuperation du temps passé sur le puzzle</Text>
					<XForm>
						<PinX Unit="MM">5.846456692913385</PinX>
						<PinY Unit="MM">6.594488188976377</PinY>
					</XForm>
					<LayerMem>
						<LayerMember>0</LayerMember>
					</LayerMem>
					<Prop ID="1" Name="Cost" NameU="Cost">
						<Value></Value>
						<Label>Coût</Label>
					</Prop>
					<Prop ID="2" Name="ProcessNumber" NameU="ProcessNumber">
						<Value></Value>
						<Label>Numéro de processus</Label>
					</Prop>
					<Prop ID="3" Name="Owner" NameU="Owner">
						<Value></Value>
						<Label>Propriétaire</Label>
					</Prop>
					<Prop ID="4" Name="Function" NameU="Function">
						<Value></Value>
						<Label>Fonction</Label>
					</Prop>
					<Prop ID="5" Name="StartDate" NameU="StartDate">
						<Value></Value>
						<Label>Date de début</Label>
					</Prop>
					<Prop ID="6" Name="EndDate" NameU="EndDate">
						<Value></Value>
						<Label>Date de fin</Label>
					</Prop>
					<Prop ID="7" Name="Status" NameU="Status">
						<Value></Value>
						<Label>État</Label>
					</Prop>
				</Shape>
				<Shape ID="5" UniqueID="{5547E12E-915B-4D6F-B463-877D0B5A07EE}" Name="Lien dynamique.5" NameU="Dynamic connector.5" Master="7">
					<XForm>
						<PinX Unit="MM">5.846456692913385</PinX>
						<PinY Unit="MM">6.003937007874013</PinY>
					</XForm>
					<LayerMem>
						<LayerMember>1</LayerMember>
					</LayerMem>
				</Shape>
				<Shape ID="4" UniqueID="{CEF96C13-FEF5-4572-B042-602702EF16E2}" Name="Processus.4" NameU="Process.4" Master="6">
					<Text>Affichage du temps passé</Text>
					<XForm>
						<PinX Unit="MM">5.846456692913385</PinX>
						<PinY Unit="MM">5.413385826771651</PinY>
					</XForm>
					<LayerMem>
						<LayerMember>0</LayerMember>
					</LayerMem>
					<Prop ID="1" Name="Cost" NameU="Cost">
						<Value></Value>
						<Label>Coût</Label>
					</Prop>
					<Prop ID="2" Name="ProcessNumber" NameU="ProcessNumber">
						<Value></Value>
						<Label>Numéro de processus</Label>
					</Prop>
					<Prop ID="3" Name="Owner" NameU="Owner">
						<Value></Value>
						<Label>Propriétaire</Label>
					</Prop>
					<Prop ID="4" Name="Function" NameU="Function">
						<Value></Value>
						<Label>Fonction</Label>
					</Prop>
					<Prop ID="5" Name="StartDate" NameU="StartDate">
						<Value></Value>
						<Label>Date de début</Label>
					</Prop>
					<Prop ID="6" Name="EndDate" NameU="EndDate">
						<Value></Value>
						<Label>Date de fin</Label>
					</Prop>
					<Prop ID="7" Name="Status" NameU="Status">
						<Value></Value>
						<Label>État</Label>
					</Prop>
				</Shape>
				<Shape ID="7" UniqueID="{9C777E80-7A21-4368-A2B3-87BAD21D212F}" Name="Lien dynamique.7" NameU="Dynamic connector.7" Master="7">
					<XForm>
						<PinX Unit="MM">5.846456692913385</PinX>
						<PinY Unit="MM">4.822834645669288</PinY>
					</XForm>
					<LayerMem>
						<LayerMember>1</LayerMember>
					</LayerMem>
				</Shape>
				<Shape ID="6" UniqueID="{2D5350CE-33AE-4F4D-86FF-7B02DE785E0C}" Name="Début/fin.6" NameU="Start/End.6" Master="2">
					<Text>Fin</Text>
					<XForm>
						<PinX Unit="MM">5.846456692913385</PinX>
						<PinY Unit="MM">4.330708661417320</PinY>
					</XForm>
					<LayerMem>
						<LayerMember>0</LayerMember>
					</LayerMem>
					<Prop ID="1" Name="Cost" NameU="Cost">
						<Value></Value>
						<Label>Coût</Label>
					</Prop>
					<Prop ID="2" Name="ProcessNumber" NameU="ProcessNumber">
						<Value></Value>
						<Label>Numéro de processus</Label>
					</Prop>
					<Prop ID="3" Name="Owner" NameU="Owner">
						<Value></Value>
						<Label>Propriétaire</Label>
					</Prop>
					<Prop ID="4" Name="Function" NameU="Function">
						<Value></Value>
						<Label>Fonction</Label>
					</Prop>
					<Prop ID="5" Name="StartDate" NameU="StartDate">
						<Value></Value>
						<Label>Date de début</Label>
					</Prop>
					<Prop ID="6" Name="EndDate" NameU="EndDate">
						<Value></Value>
						<Label>Date de fin</Label>
					</Prop>
					<Prop ID="7" Name="Status" NameU="Status">
						<Value></Value>
						<Label>État</Label>
					</Prop>
				</Shape>
			</Shapes>
		</Page>
		<Page ID="11" Name="Capture d'écran" NameU="Capture d'écran">
			<PageProps>
				<PageScale Unit="MM">0.039370078740157</PageScale>
				<DrawingScale Unit="MM">0.039370078740157</DrawingScale>
			</PageProps>
			<Layer IX="0">
				<Name>Diagramme de flux</Name>
				<NameUniv>Flowchart</NameUniv>
				<Visible>1</Visible>
			</Layer>
			<Layer IX="1">
				<Name>Lien</Name>
				<NameUniv>Connector</NameUniv>
				<Visible>1</Visible>
			</Layer>
			<Shapes>
				<Shape ID="1" UniqueID="{2376BC4B-6ABE-4F95-A784-7D3014B8A65F}" Name="Début/fin" NameU="Start/End" Master="2">
					<Text>début</Text>
					<XForm>
						<PinX Unit="MM">5.846456692913385</PinX>
						<PinY Unit="MM">7.677165354330707</PinY>
					</XForm>
					<LayerMem>
						<LayerMember>0</LayerMember>
					</LayerMem>
					<Prop ID="1" Name="Cost" NameU="Cost">
						<Value></Value>
						<Label>Coût</Label>
					</Prop>
					<Prop ID="2" Name="ProcessNumber" NameU="ProcessNumber">
						<Value></Value>
						<Label>Numéro de processus</Label>
					</Prop>
					<Prop ID="3" Name="Owner" NameU="Owner">
						<Value></Value>
						<Label>Propriétaire</Label>
					</Prop>
					<Prop ID="4" Name="Function" NameU="Function">
						<Value></Value>
						<Label>Fonction</Label>
					</Prop>
					<Prop ID="5" Name="StartDate" NameU="StartDate">
						<Value></Value>
						<Label>Date de début</Label>
					</Prop>
					<Prop ID="6" Name="EndDate" NameU="EndDate">
						<Value></Value>
						<Label>Date de fin</Label>
					</Prop>
					<Prop ID="7" Name="Status" NameU="Status">
						<Value></Value>
						<Label>État</Label>
					</Prop>
				</Shape>
				<Shape ID="3" UniqueID="{59444DE5-19E9-4F60-838F-DBDA052364AE}" Name="Lien dynamique" NameU="Dynamic connector" Master="7">
					<XForm>
						<PinX Unit="MM">5.846456692913385</PinX>
						<PinY Unit="MM">7.185039370078739</PinY>
					</XForm>
					<LayerMem>
						<LayerMember>1</LayerMember>
					</LayerMem>
				</Shape>
				<Shape ID="2" UniqueID="{3BF7D287-41C2-4829-BF1F-F7DD457A23AC}" Name="Processus" NameU="Process" Master="6">
					<Text>Prend en photo le puzzle</Text>
					<XForm>
						<PinX Unit="MM">5.846456692913385</PinX>
						<PinY Unit="MM">6.594488188976377</PinY>
					</XForm>
					<LayerMem>
						<LayerMember>0</LayerMember>
					</LayerMem>
					<Prop ID="1" Name="Cost" NameU="Cost">
						<Value></Value>
						<Label>Coût</Label>
					</Prop>
					<Prop ID="2" Name="ProcessNumber" NameU="ProcessNumber">
						<Value></Value>
						<Label>Numéro de processus</Label>
					</Prop>
					<Prop ID="3" Name="Owner" NameU="Owner">
						<Value></Value>
						<Label>Propriétaire</Label>
					</Prop>
					<Prop ID="4" Name="Function" NameU="Function">
						<Value></Value>
						<Label>Fonction</Label>
					</Prop>
					<Prop ID="5" Name="StartDate" NameU="StartDate">
						<Value></Value>
						<Label>Date de début</Label>
					</Prop>
					<Prop ID="6" Name="EndDate" NameU="EndDate">
						<Value></Value>
						<Label>Date de fin</Label>
					</Prop>
					<Prop ID="7" Name="Status" NameU="Status">
						<Value></Value>
						<Label>État</Label>
					</Prop>
				</Shape>
				<Shape ID="4" UniqueID="{816CCD1F-4BF6-493E-8BA2-87E24DAAF574}" Name="Processus.4" NameU="Process.4" Master="6">
					<Text>Sauvegarde la capture sur le disque</Text>
					<XForm>
						<PinX Unit="MM">5.846456692913385</PinX>
						<PinY Unit="MM">5.413385826771652</PinY>
					</XForm>
					<LayerMem>
						<LayerMember>0</LayerMember>
					</LayerMem>
					<Prop ID="1" Name="Cost" NameU="Cost">
						<Value></Value>
						<Label>Coût</Label>
					</Prop>
					<Prop ID="2" Name="ProcessNumber" NameU="ProcessNumber">
						<Value></Value>
						<Label>Numéro de processus</Label>
					</Prop>
					<Prop ID="3" Name="Owner" NameU="Owner">
						<Value></Value>
						<Label>Propriétaire</Label>
					</Prop>
					<Prop ID="4" Name="Function" NameU="Function">
						<Value></Value>
						<Label>Fonction</Label>
					</Prop>
					<Prop ID="5" Name="StartDate" NameU="StartDate">
						<Value></Value>
						<Label>Date de début</Label>
					</Prop>
					<Prop ID="6" Name="EndDate" NameU="EndDate">
						<Value></Value>
						<Label>Date de fin</Label>
					</Prop>
					<Prop ID="7" Name="Status" NameU="Status">
						<Value></Value>
						<Label>État</Label>
					</Prop>
				</Shape>
				<Shape ID="5" UniqueID="{87C32ADA-6AC0-4313-AAB3-2FC186FC2C0A}" Name="Lien dynamique.5" NameU="Dynamic connector.5" Master="7">
					<XForm>
						<PinX Unit="MM">5.846456692913385</PinX>
						<PinY Unit="MM">6.003937007874013</PinY>
					</XForm>
					<LayerMem>
						<LayerMember>1</LayerMember>
					</LayerMem>
				</Shape>
				<Shape ID="7" UniqueID="{D3C05384-55ED-4E76-8307-3C04BC429BA8}" Name="Lien dynamique.7" NameU="Dynamic connector.7" Master="7">
					<XForm>
						<PinX Unit="MM">5.846456692913385</PinX>
						<PinY Unit="MM">4.822834645669290</PinY>
					</XForm>
					<LayerMem>
						<LayerMember>1</LayerMember>
					</LayerMem>
				</Shape>
				<Shape ID="6" UniqueID="{646E1ED8-B212-4A65-B9CF-BD63DF067A5A}" Name="Début/fin.6" NameU="Start/End.6" Master="2">
					<Text>Fin</Text>
					<XForm>
						<PinX Unit="MM">5.846456692913385</PinX>
						<PinY Unit="MM">4.330708661417321</PinY>
					</XForm>
					<LayerMem>
						<LayerMember>0</LayerMember>
					</LayerMem>
					<Prop ID="1" Name="Cost" NameU="Cost">
						<Value></Value>
						<Label>Coût</Label>
					</Prop>
					<Prop ID="2" Name="ProcessNumber" NameU="ProcessNumber">
						<Value></Value>
						<Label>Numéro de processus</Label>
					</Prop>
					<Prop ID="3" Name="Owner" NameU="Owner">
						<Value></Value>
						<Label>Propriétaire</Label>
					</Prop>
					<Prop ID="4" Name="Function" NameU="Function">
						<Value></Value>
						<Label>Fonction</Label>
					</Prop>
					<Prop ID="5" Name="StartDate" NameU="StartDate">
						<Value></Value>
						<Label>Date de début</Label>
					</Prop>
					<Prop ID="6" Name="EndDate" NameU="EndDate">
						<Value></Value>
						<Label>Date de fin</Label>
					</Prop>
					<Prop ID="7" Name="Status" NameU="Status">
						<Value></Value>
						<Label>État</Label>
					</Prop>
				</Shape>
			</Shapes>
		</Page>
	</Pages>
</VisioDocument>
